Workbook

Sheet README
A1: EnergyWave, Inc. — Next-Raise Budget, Forecast & Due-Diligence Workbook · v1 · 2026-09-07
A2: Prepared for Ian McLean (Founder & CEO) and the interim finance team (E57 Partners or equivalent). Driver-based, 36-month, scenario-switched.
A4: WHAT THIS IS
A5: A monthly cash-need plan for EnergyWave, Inc. only. It computes the raise size from the plan (headcount + lab + equipment + G&A + reserve) and tranches it by the three research gates, so the packet shows dollars tied to milestones rather than an open-ended ask.
A6: It contains NO device performance claims and NO technical specifications. Nothing in this file is a statement about what any configuration under test does.
A8: CONVENTIONS
A9: Blue text = input you can change. Black = formula (do not overwrite). Green = link to another sheet. Yellow fill = key lever / headline output.
A10: Every dollar input carries an 'Input status': 'From Ian' = number Ian gave; 'Placeholder' = my estimate to be validated by finance; 'Formula' = computed. Treat every Placeholder as unvalidated.
A11: Scenario lever: Assumptions!B4 (1 = Lean, 2 = Base, 3 = Full). It changes start months and equipment tiers everywhere; nothing else needs touching.
A13: SHEETS
A14: Assumptions — global drivers (scenario, start date, payroll load, reserve %, gate months, rent, recruiting fee, outsourced-finance fees).
A15: Headcount — every role with base, load flag, relocation, equity note, start month by scenario, monthly cost, 36-month total.
... A35: 6. Intercompany line stays $0 until Novak confirms the arms-length structure for both nonprofits.

Sheet Assumptions
A1: Assumptions — global drivers
A2: Blue = input. Yellow = scenario lever / headline. Status column says where each number came from.
A3: Driver | B3: Value | C3: Unit / notes | D3: Input status
A4: Scenario (1 = Lean, 2 = Base, 3 = Full) | B4: 2 | C4: Drives start months and equipment tiers everywhere | D4: Lever
A5: Model start (month 1) | B5: 46388 | C5: First month of spend after close — change freely | D5: Placeholder
A6: Horizon (months) — fixed by layout | B6: 36 | C6: Monthly sheet has 36 columns; do not change | D6: Fixed
A7: Payroll load (benefits + employer taxes) | B7: 0.22 | C7: Applied to W-2 base only | D7: Placeholder
A8: Default relocation per relocating hire | B8: 25000 | C8: Applied to the five applied-physicist hires; override per row on Headcount | D8: Placeholder
A9: Option pool (% fully diluted) — non-cash | B9: 0.12 | C9: Cap-table item, not a cash line; recorded for the packet | D9: Placeholder
A10: Reserve / contingency (% of plan spend) | B10: 0.2 | C10: Added to plan spend to size the raise | D10: Placeholder
A11: Gate 1 — Characterize complete (month) | B11: 9 | C11: Three-gate protocol milestone; drives tranche table | D11: Placeholder
A12: Gate 2 — Conservation test complete (month) | B12: 21 | D12: Placeholder
A13: Gate 3 — Extract or retire, published (month) | B13: 36 | D13: Placeholder
A14: Facility size (sq ft) | B14: 6000 | C14: Office + lab near UCI (University Research Park, Irvine) | D14: Placeholder
A15: Facility rate ($ per sq ft per month, full service) | B15: 3.75 | C15: Verify current University Research Park asking rates; lab-grade space runs higher | D15: Placeholder
A16: Facility rent (monthly) | B16: =B14*B15 -> 22500 | D16: Formula
A17: Security deposit (months of rent) | B17: 2 | D17: Placeholder
A18: Recruiting fee (% of first-year base, search firm) | B18: 0.2 | C18: Applied to the five applied-physicist hires | D18: Placeholder
A19: Outsourced finance (E57 or equivalent) — months 1–6 | B19: 25000 | C19: FP&A build + fractional controller, build phase; get E57's actual quote | D19: Placeholder
A20: Outsourced finance — month 7 onward | B20: 15000 | C20: Maintenance phase | D20: Placeholder
A21: Scenario name | B21: =CHOOSE(B4,"Lean","Base","Full") -> Base | D21: Formula

Sheet Headcount
A1: Headcount & consulting plan
A2: Blue = input. Start month = first month of cost (1 = model start). Equity is non-cash (cap table). 'Load?' = Y applies payroll load to base.
A3: ID | B3: Role | C3: Person / status | D3: Entity | E3: Type | F3: Annual base ($) | G3: Load? (Y/N) | H3: Relocation ($, one-time) | I3: Equity (non-cash) | J3: Start — Lean | K3: Start — Base | L3: Start — Full | M3: Start (selected) | N3: Monthly cost ($) | O3: 36-mo total ($) | P3: Discipline target / notes | Q3: Input status
A4: H01 | B4: Founder & CEO | C4: Ian F. McLean | D4: EnergyWave, Inc. | E4: W-2 | F4: 240000 | G4: Y | H4: 0 | I4: Founder | J4: 1 | K4: 1 | L4: 1 | M4: =CHOOSE(Scenario,J4,K4,L4) -> 1 | N4: =IF(G4="Y",F4*(1+LoadPct),F4)/12 -> 24400 | O4: =N4*MAX(0,Horizon-M4+1)+H4 -> 878400 | P4: Founder salary — set to an investor-acceptable level; pre-seed SAFE covered runway | Q4: Placeholder
A5: H02 | B5: Co-founder / Research Director (part-time) | C5: Kenneth "Chip" Story | D5: EnergyWave, Inc. | E5: 1099 | F5: 150000 | G5: N | H5: 0 | I5: Founder | J5: 1 | K5: 1 | L5: 1 | M5: =CHOOSE(Scenario,J5,K5,L5) -> 1 | N5: =IF(G5="Y",F5*(1+LoadPct),F5)/12 -> 12500 | O5: =N5*MAX(0,Horizon-M5+1)+H5 -> 450000 | P5: Confirm role, time commitment, cash vs. equity; document ZPEPG boundary (IP, conflicts) | Q5: Placeholder
A6: H03 | B6: Applied Physicist 1 | C6: Open requisition | D6: EnergyWave, Inc. | E6: W-2 | F6: 150000 | G6: Y | H6: =RelocDefault -> 25000 | I6: Pool | J6: 3 | K6: 2 | L6: 1 | M6: =CHOOSE(Scenario,J6,K6,L6) -> 2 | N6: =IF(G6="Y",F6*(1+LoadPct),F6)/12 -> 15250 | O6: =N6*MAX(0,Horizon-M6+1)+H6 -> 558750 | P6: Physics + mathematics + neuroscience (Ian's target mix) | Q6: From Ian (base); reloc placeholder
A7: H04 | B7: Applied Physicist 2 | C7: Open requisition | D7: EnergyWave, Inc. | E7: W-2 | F7: 150000 | G7: Y | H7: =RelocDefault -> 25000 | I7: Pool | J7: 4 | K7: 2 | L7: 1 | M7: =CHOOSE(Scenario,J7,K7,L7) -> 2 | N7: =IF(G7="Y",F7*(1+LoadPct),F7)/12 -> 15250 | O7: =N7*MAX(0,Horizon-M7+1)+H7 -> 558750 | P7: Physics + mechanical engineering + materials science | Q7: From Ian (base); reloc placeholder
A8: H05 | B8: Applied Physicist 3 | C8: Open requisition | D8: EnergyWave, Inc. | E8: W-2 | F8: 150000 | G8: Y | H8: =RelocDefault -> 25000 | I8: Pool | J8: 6 | K8: 3 | L8: 2 | M8: =CHOOSE(Scenario,J8,K8,L8) -> 3 | N8: =IF(G8="Y",F8*(1+LoadPct),F8)/12 -> 15250 | O8: =N8*MAX(0,Horizon-M8+1)+H8 -> 543500 | P8: Physics + materials science; calorimetry / thermal measurement | Q8: From Ian (base); reloc placeholder
A9: H06 | B9: Applied Physicist 4 | C9: Open requisition | D9: EnergyWave, Inc. | E9: W-2 | F9: 150000 | G9: Y | H9: =RelocDefault -> 25000 | I9: Pool | J9: 8 | K9: 4 | L9: 2 | M9: =CHOOSE(Scenario,J9,K9,L9) -> 4 | N9: =IF(G9="Y",F9*(1+LoadPct),F9)/12 -> 15250 | O9: =N9*MAX(0,Horizon-M9+1)+H9 -> 528250 | P9: Physics + electrical engineering; power electronics, precision measurement | Q9: From Ian (base); reloc placeholder
A10: H07 | B10: Applied Physicist 5 | C10: Open requisition | D10: EnergyWave, Inc. | E10: W-2 | F10: 150000 | G10: Y | H10: =RelocDefault -> 25000 | I10: Pool | J10: 10 | K10: 5 | L10: 3 | M10: =CHOOSE(Scenario,J10,K10,L10) -> 5 | N10: =IF(G10="Y",F10*(1+LoadPct),F10)/12 -> 15250 | O10: =N10*MAX(0,Horizon-M10+1)+H10 -> 513000 | P10: Physics + mathematics; statistics, null-result experimental design | Q10: From Ian (base); reloc placeholder
A11: H08 | B11: Theoretical Physicist — consulting agreement 1 | C11: Open | D11: EnergyWave, Inc. | E11: 1099 | F11: 500000 | G11: N | H11: 0 | I11: TBD | J11: 2 | K11: 1 | L11: 1 | M11: =CHOOSE(Scenario,J11,K11,L11) -> 1 | N11: =IF(G11="Y",F11*(1+LoadPct),F11)/12 -> 41666.667 | O11: =N11*MAX(0,Horizon-M11+1)+H11 -> 1500000 | P11: Ian: ~$500k/yr consulting agreement. Modeled as $500k EACH — confirm each vs. total | Q11: From Ian (interpretation flagged)
A12: H09 | B12: Theoretical Physicist — consulting agreement 2 | C12: Open | D12: EnergyWave, Inc. | E12: 1099 | F12: 500000 | G12: N | H12: 0 | I12: TBD | J12: 4 | K12: 3 | L12: 1 | M12: =CHOOSE(Scenario,J12,K12,L12) -> 3 | N12: =IF(G12="Y",F12*(1+LoadPct),F12)/12 -> 41666.667 | O12: =N12*MAX(0,Horizon-M12+1)+H12 -> 1416666.7 | P12: As above | Q12: From Ian (interpretation flagged)
A13: H10 | B13: Lab Safety / EHS Officer | C13: Open requisition | D13: EnergyWave, Inc. | E13: W-2 | F13: 120000 | G13: Y | H13: 10000 | I13: Pool | J13: 2 | K13: 1 | L13: 1 | M13: =CHOOSE(Scenario,J13,K13,L13) -> 1 | N13: =IF(G13="Y",F13*(1+LoadPct),F13)/12 -> 12200 | O13: =N13*MAX(0,Horizon-M13+1)+H13 -> 449200 | P13: Must precede lab operations; owns hazard review, test protocols, incident reporting | Q13: Placeholder
A14: H11 | B14: Test & Instrumentation Engineer 1 (calorimetry) | C14: Open requisition | D14: EnergyWave, Inc. | E14: W-2 | F14: 135000 | G14: Y | H14: 15000 | I14: Pool | J14: 3 | K14: 2 | L14: 1 | M14: =CHOOSE(Scenario,J14,K14,L14) -> 2 | N14: =IF(G14="Y",F14*(1+LoadPct),F14)/12 -> 13725 | O14: =N14*MAX(0,Horizon-M14+1)+H14 -> 495375 | P14: Calorimetry, DAQ, calibration discipline | Q14: Placeholder
A15: H12 | B15: Test & Instrumentation Engineer 2 | C15: Open requisition | D15: EnergyWave, Inc. | E15: W-2 | F15: 135000 | G15: Y | H15: 15000 | I15: Pool | J15: 6 | K15: 4 | L15: 2 | M15: =CHOOSE(Scenario,J15,K15,L15) -> 4 | N15: =IF(G15="Y",F15*(1+LoadPct),F15)/12 -> 13725 | O15: =N15*MAX(0,Horizon-M15+1)+H15 -> 467925 | P15: Second bench; independent replication of in-house measurements | Q15: Placeholder
A16: H13 | B16: Additive Manufacturing Engineer | C16: Open requisition | D16: EnergyWave, Inc. | E16: W-2 | F16: 140000 | G16: Y | H16: 15000 | I16: Pool | J16: 5 | K16: 3 | L16: 2 | M16: =CHOOSE(Scenario,J16,K16,L16) -> 3 | N16: =IF(G16="Y",F16*(1+LoadPct),F16)/12 -> 14233.333 | O16: =N16*MAX(0,Horizon-M16+1)+H16 -> 498933.33 | P16: Runs the precision AM system; process-parameter optimization | Q16: Placeholder
A17: H14 | B17: Software / Algorithms Engineer | C17: Open requisition | D17: EnergyWave, Inc. | E17: W-2 | F17: 160000 | G17: Y | H17: 15000 | I17: Pool | J17: 4 | K17: 3 | L17: 2 | M17: =CHOOSE(Scenario,J17,K17,L17) -> 3 | N17: =IF(G17="Y",F17*(1+LoadPct),F17)/12 -> 16266.667 | O17: =N17*MAX(0,Horizon-M17+1)+H17 -> 568066.67 | P17: Closed-loop AM parameter search, DAQ pipelines, data integrity / audit trail | Q17: Placeholder
A18: H15 | B18: Lab Technician | C18: Open requisition | D18: EnergyWave, Inc. | E18: W-2 | F18: 85000 | G18: Y | H18: 0 | I18: Pool | J18: 7 | K18: 4 | L18: 3 | M18: =CHOOSE(Scenario,J18,K18,L18) -> 4 | N18: =IF(G18="Y",F18*(1+LoadPct),F18)/12 -> 8641.6667 | O18: =N18*MAX(0,Horizon-M18+1)+H18 -> 285175 | Q18: Placeholder
A19: H16 | B19: Executive Assistant | C19: Open requisition | D19: EnergyWave, Inc. | E19: W-2 | F19: 85000 | G19: Y | H19: 0 | I19: Pool | J19: 2 | K19: 1 | L19: 1 | M19: =CHOOSE(Scenario,J19,K19,L19) -> 1 | N19: =IF(G19="Y",F19*(1+LoadPct),F19)/12 -> 8641.6667 | O19: =N19*MAX(0,Horizon-M19+1)+H19 -> 311100 | Q19: Placeholder
A20: H17 | B20: Office & Operations Coordinator | C20: Open requisition | D20: EnergyWave, Inc. | E20: W-2 | F20: 70000 | G20: Y | H20: 0 | I20: Pool | J20: 4 | K20: 2 | L20: 1 | M20: =CHOOSE(Scenario,J20,K20,L20) -> 2 | N20: =IF(G20="Y",F20*(1+LoadPct),F20)/12 -> 7116.6667 | O20: =N20*MAX(0,Horizon-M20+1)+H20 -> 249083.33 | Q20: Placeholder
A21: H18 | B21: Government Liaison (consulting) | C21: Eric Fitzgerald | D21: EnergyWave, Inc. | E21: 1099 | F21: 60000 | G21: N | H21: 0 | I21: TBD | J21: 2 | K21: 1 | L21: 1 | M21: =CHOOSE(Scenario,J21,K21,L21) -> 1 | N21: =IF(G21="Y",F21*(1+LoadPct),F21)/12 -> 5000 | O21: =N21*MAX(0,Horizon-M21+1)+H21 -> 180000 | P21: Confirm engagement terms (cash vs. equity); lobbying-disclosure check | Q21: Placeholder
B22: Total | F22: =SUM(F4:F21) -> 3130000 | H22: =SUM(H4:H21) -> 195000 | N22: =SUM(N4:N21) -> 296033.33 | O22: =SUM(O4:O21) -> 10452175
B24: Legend: Start month is the first month the cost hits. Monthly cost = base × (1 + load) / 12 for W-2, base / 12 for 1099. 36-mo total = monthly × months remaining + relocation.
B25: Equity: 'Pool' = grant from the option pool (Assumptions!B9); 'Founder' = founder stock; 'TBD' = advisor/consultant grant to be decided. None of this is cash.

Sheet CostLines
A1: Non-payroll cost lines (facilities, equipment, research, legal, finance, G&A)
A2: Blue = input. Type: Monthly (recurs from start), One-time (hits start month only), Annual (spread 1/12 per month from start). Blank duration = through horizon.
A3: ID | B3: Line item | C3: Entity | D3: Category | E3: Subcategory | F3: Type | G3: Lean ($) | H3: Base ($) | I3: Full ($) | J3: Selected ($) | K3: Start — Lean | L3: Start — Base | M3: Start — Full | N3: Start (selected) | O3: Duration (months; blank = to end) | P3: Monthly equiv. ($) | Q3: 36-mo total ($) | R3: Notes | S3: Input status
A4: C01 | B4: Office + lab lease near UCI (University Research Park) | C4: EnergyWave, Inc. | D4: Facilities | E4: Lease | F4: Monthly | G4: =RentMonthly -> 22500 | H4: =RentMonthly -> 22500 | I4: =RentMonthly -> 22500 | J4: =CHOOSE(Scenario,G4,H4,I4) -> 22500 | K4: 3 | L4: 2 | M4: 1 | N4: =CHOOSE(Scenario,K4,L4,M4) -> 2 | P4: =IF(F4="Monthly",J4,IF(F4="Annual",J4/12,0)) -> 22500 | Q4: =IF(F4="One-time",IF(N4<=Horizon,J4,0),P4*MAX(0,MIN(Horizon,IF(O4="",Horizon,N4+O4-1))-N4+1)) -> 787500 | R4: 6,000 sf × $3.75/sf/mo full service (Assumptions). Lab-grade space with power/ventilation may price higher. | S4: Placeholder
A5: C02 | B5: Security deposit | C5: EnergyWave, Inc. | D5: Facilities | E5: Deposit | F5: One-time | G5: =RentMonthly*DepositMonths -> 45000 | H5: =RentMonthly*DepositMonths -> 45000 | I5: =RentMonthly*DepositMonths -> 45000 | J5: =CHOOSE(Scenario,G5,H5,I5) -> 45000 | K5: 3 | L5: 2 | M5: 1 | N5: =CHOOSE(Scenario,K5,L5,M5) -> 2 | P5: =IF(F5="Monthly",J5,IF(F5="Annual",J5/12,0)) -> 0 | Q5: =IF(F5="One-time",IF(N5<=Horizon,J5,0),P5*MAX(0,MIN(Horizon,IF(O5="",Horizon,N5+O5-1))-N5+1)) -> 45000 | R5: Months of rent per Assumptions | S5: Formula
A6: C03 | B6: Lab build-out (power, ventilation, benches, shielding) | C6: EnergyWave, Inc. | D6: Facilities | E6: Build-out | F6: One-time | G6: 150000 | H6: 300000 | I6: 600000 | J6: =CHOOSE(Scenario,G6,H6,I6) -> 300000 | K6: 3 | L6: 2 | M6: 1 | N6: =CHOOSE(Scenario,K6,L6,M6) -> 2 | P6: =IF(F6="Monthly",J6,IF(F6="Annual",J6/12,0)) -> 0 | Q6: =IF(F6="One-time",IF(N6<=Horizon,J6,0),P6*MAX(0,MIN(Horizon,IF(O6="",Horizon,N6+O6-1))-N6+1)) -> 300000 | R6: Tenant-improvement scope TBD with landlord; partly offsettable by TI allowance | S6: Placeholder
A7: C04 | B7: Utilities, internet, security | C7: EnergyWave, Inc. | D7: Facilities | E7: Utilities | F7: Monthly | G7: 3000 | H7: 4000 | I7: 6000 | J7: =CHOOSE(Scenario,G7,H7,I7) -> 4000 | K7: 3 | L7: 2 | M7: 1 | N7: =CHOOSE(Scenario,K7,L7,M7) -> 2 | P7: =IF(F7="Monthly",J7,IF(F7="Annual",J7/12,0)) -> 4000 | Q7: =IF(F7="One-time",IF(N7<=Horizon,J7,0),P7*MAX(0,MIN(Horizon,IF(O7="",Horizon,N7+O7-1))-N7+1)) -> 140000 | S7: Placeholder
A8: C05 | B8: Tabletop instrumentation package (calorimeters, power analyzers, precision sources/loads, DAQ, thermal chambers, balances, shielded enclosure, reference standards) | C8: EnergyWave, Inc. | D8: Equipment | E8: Instrumentation | F8: One-time | G8: 250000 | H8: 450000 | I8: 750000 | J8: =CHOOSE(Scenario,G8,H8,I8) -> 450000 | K8: 3 | L8: 2 | M8: 1 | N8: =CHOOSE(Scenario,K8,L8,M8) -> 2 | P8: =IF(F8="Monthly",J8,IF(F8="Annual",J8/12,0)) -> 0 | Q8: =IF(F8="One-time",IF(N8<=Horizon,J8,0),P8*MAX(0,MIN(Horizon,IF(O8="",Horizon,N8+O8-1))-N8+1)) -> 450000 | R8: Package, not a spec list. Priced for conservation-of-energy measurement, not for any device claim. | S8: Placeholder
A9: C06 | B9: Calibration & metrology services | C9: EnergyWave, Inc. | D9: Equipment | E9: Calibration | F9: Annual | G9: 20000 | H9: 30000 | I9: 45000 | J9: =CHOOSE(Scenario,G9,H9,I9) -> 30000 | K9: 4 | L9: 3 | M9: 2 | N9: =CHOOSE(Scenario,K9,L9,M9) -> 3 | P9: =IF(F9="Monthly",J9,IF(F9="Annual",J9/12,0)) -> 2500 | Q9: =IF(F9="One-time",IF(N9<=Horizon,J9,0),P9*MAX(0,MIN(Horizon,IF(O9="",Horizon,N9+O9-1))-N9+1)) -> 85000 | R9: Traceable calibration is what makes a null result publishable | S9: Placeholder
A10: C07 | B10: Precision additive-manufacturing system (high-resolution AM with closed-loop process control) | C10: EnergyWave, Inc. | D10: Equipment | E10: Additive manufacturing | F10: One-time | G10: 350000 | H10: 750000 | I10: 1500000 | J10: =CHOOSE(Scenario,G10,H10,I10) -> 750000 | K10: 5 | L10: 3 | M10: 2 | N10: =CHOOSE(Scenario,K10,L10,M10) -> 3 | P10: =IF(F10="Monthly",J10,IF(F10="Annual",J10/12,0)) -> 0 | Q10: =IF(F10="One-time",IF(N10<=Horizon,J10,0),P10*MAX(0,MIN(Horizon,IF(O10="",Horizon,N10+O10-1))-N10+1)) -> 750000 | R10: Class/vendor TBD (micro-scale polymer/metal vs. metal laser powder-bed). Placeholder = mid-range list price. | S10: Placeholder
A11: C08 | B11: AM service contract & software | C11: EnergyWave, Inc. | D11: Equipment | E11: Additive manufacturing | F11: Annual | G11: 30000 | H11: 40000 | I11: 60000 | J11: =CHOOSE(Scenario,G11,H11,I11) -> 40000 | K11: 6 | L11: 4 | M11: 3 | N11: =CHOOSE(Scenario,K11,L11,M11) -> 4 | P11: =IF(F11="Monthly",J11,IF(F11="Annual",J11/12,0)) -> 3333.3333 | Q11: =IF(F11="One-time",IF(N11<=Horizon,J11,0),P11*MAX(0,MIN(Horizon,IF(O11="",Horizon,N11+O11-1))-N11+1)) -> 110000 | S11: Placeholder
A12: C09 | B12: AM feedstock & lab consumables | C12: EnergyWave, Inc. | D12: Operations | E12: Consumables | F12: Monthly | G12: 6000 | H12: 10000 | I12: 16000 | J12: =CHOOSE(Scenario,G12,H12,I12) -> 10000 | K12: 4 | L12: 3 | M12: 2 | N12: =CHOOSE(Scenario,K12,L12,M12) -> 3 | P12: =IF(F12="Monthly",J12,IF(F12="Annual",J12/12,0)) -> 10000 | Q12: =IF(F12="One-time",IF(N12<=Horizon,J12,0),P12*MAX(0,MIN(Horizon,IF(O12="",Horizon,N12+O12-1))-N12+1)) -> 340000 | S12: Placeholder
A13: C10 | B13: Compute, simulation & software licenses | C13: EnergyWave, Inc. | D13: Operations | E13: Compute | F13: Monthly | G13: 5000 | H13: 8000 | I13: 12000 | J13: =CHOOSE(Scenario,G13,H13,I13) -> 8000 | K13: 1 | L13: 1 | M13: 1 | N13: =CHOOSE(Scenario,K13,L13,M13) -> 1 | P13: =IF(F13="Monthly",J13,IF(F13="Annual",J13/12,0)) -> 8000 | Q13: =IF(F13="One-time",IF(N13<=Horizon,J13,0),P13*MAX(0,MIN(Horizon,IF(O13="",Horizon,N13+O13-1))-N13+1)) -> 288000 | S13: Placeholder
A14: C11 | B14: Independent third-party replication / verification | C14: EnergyWave, Inc. | D14: Research | E14: External verification | F14: Annual | G14: 100000 | H14: 150000 | I14: 250000 | J14: =CHOOSE(Scenario,G14,H14,I14) -> 150000 | K14: 9 | L14: 7 | M14: 5 | N14: =CHOOSE(Scenario,K14,L14,M14) -> 7 | P14: =IF(F14="Monthly",J14,IF(F14="Annual",J14/12,0)) -> 12500 | Q14: =IF(F14="One-time",IF(N14<=Horizon,J14,0),P14*MAX(0,MIN(Horizon,IF(O14="",Horizon,N14+O14-1))-N14+1)) -> 375000 | R14: Core to claims discipline; results published either direction | S14: Placeholder
A15: C12 | B15: UCI / NFCRC facility-use or sponsored-research agreement | C15: EnergyWave, Inc. | D15: Research | E15: University partnership | F15: Annual | G15: 75000 | H15: 150000 | I15: 300000 | J15: =CHOOSE(Scenario,G15,H15,I15) -> 150000 | K15: 4 | L15: 3 | M15: 2 | N15: =CHOOSE(Scenario,K15,L15,M15) -> 3 | P15: =IF(F15="Monthly",J15,IF(F15="Annual",J15/12,0)) -> 12500 | Q15: =IF(F15="One-time",IF(N15<=Horizon,J15,0),P15*MAX(0,MIN(Horizon,IF(O15="",Horizon,N15+O15-1))-N15+1)) -> 425000 | R15: Only exists if an agreement is executed; proximity alone offsets nothing. Also the STTR path. | S15: Placeholder
A16: C13 | B16: K&L Gates IP retainer (Novak / Majewski) | C16: EnergyWave, Inc. | D16: Legal | E16: IP | F16: Monthly | G16: 10000 | H16: 15000 | I16: 20000 | J16: =CHOOSE(Scenario,G16,H16,I16) -> 15000 | K16: 1 | L16: 1 | M16: 1 | N16: =CHOOSE(Scenario,K16,L16,M16) -> 1 | P16: =IF(F16="Monthly",J16,IF(F16="Annual",J16/12,0)) -> 15000 | Q16: =IF(F16="One-time",IF(N16<=Horizon,J16,0),P16*MAX(0,MIN(Horizon,IF(O16="",Horizon,N16+O16-1))-N16+1)) -> 540000 | R16: Confirm current retainer terms | S16: Placeholder
A17: C14 | B17: Entity work: 501(c)(3) determinations, intercompany / services agreements | C17: EnergyWave, Inc. | D17: Legal | E17: Corporate | F17: One-time | G17: 40000 | H17: 60000 | I17: 90000 | J17: =CHOOSE(Scenario,G17,H17,I17) -> 60000 | K17: 1 | L17: 1 | M17: 1 | N17: =CHOOSE(Scenario,K17,L17,M17) -> 1 | P17: =IF(F17="Monthly",J17,IF(F17="Annual",J17/12,0)) -> 0 | Q17: =IF(F17="One-time",IF(N17<=Horizon,J17,0),P17*MAX(0,MIN(Horizon,IF(O17="",Horizon,N17+O17-1))-N17+1)) -> 60000 | R17: Covers EW share only; nonprofits fund their own | S17: Placeholder
A18: C15 | B18: Securities counsel (raise docs, Wyoming pooling LLC, SAFE conversion) | C18: EnergyWave, Inc. | D18: Legal | E18: Securities | F18: One-time | G18: 50000 | H18: 75000 | I18: 125000 | J18: =CHOOSE(Scenario,G18,H18,I18) -> 75000 | K18: 1 | L18: 1 | M18: 1 | N18: =CHOOSE(Scenario,K18,L18,M18) -> 1 | P18: =IF(F18="Monthly",J18,IF(F18="Annual",J18/12,0)) -> 0 | Q18: =IF(F18="One-time",IF(N18<=Horizon,J18,0),P18*MAX(0,MIN(Horizon,IF(O18="",Horizon,N18+O18-1))-N18+1)) -> 75000 | R18: Joseph Johnson | S18: Placeholder
A19: C16 | B19: Ongoing corporate / employment counsel | C19: EnergyWave, Inc. | D19: Legal | E19: Corporate | F19: Monthly | G19: 3000 | H19: 5000 | I19: 8000 | J19: =CHOOSE(Scenario,G19,H19,I19) -> 5000 | K19: 2 | L19: 1 | M19: 1 | N19: =CHOOSE(Scenario,K19,L19,M19) -> 1 | P19: =IF(F19="Monthly",J19,IF(F19="Annual",J19/12,0)) -> 5000 | Q19: =IF(F19="One-time",IF(N19<=Horizon,J19,0),P19*MAX(0,MIN(Horizon,IF(O19="",Horizon,N19+O19-1))-N19+1)) -> 180000 | S19: Placeholder
A20: C17 | B20: Outsourced finance (E57 or equivalent) — build phase | C20: EnergyWave, Inc. | D20: Finance | E20: Outsourced finance | F20: Monthly | G20: =FinPhase1 -> 25000 | H20: =FinPhase1 -> 25000 | I20: =FinPhase1 -> 25000 | J20: =CHOOSE(Scenario,G20,H20,I20) -> 25000 | K20: 1 | L20: 1 | M20: 1 | N20: =CHOOSE(Scenario,K20,L20,M20) -> 1 | O20: 6 | P20: =IF(F20="Monthly",J20,IF(F20="Annual",J20/12,0)) -> 25000 | Q20: =IF(F20="One-time",IF(N20<=Horizon,J20,0),P20*MAX(0,MIN(Horizon,IF(O20="",Horizon,N20+O20-1))-N20+1)) -> 150000 | R20: Interim FP&A + fractional controller; replace with E57's quote | S20: Placeholder
A21: C18 | B21: Outsourced finance (E57 or equivalent) — maintenance | C21: EnergyWave, Inc. | D21: Finance | E21: Outsourced finance | F21: Monthly | G21: =FinPhase2 -> 15000 | H21: =FinPhase2 -> 15000 | I21: =FinPhase2 -> 15000 | J21: =CHOOSE(Scenario,G21,H21,I21) -> 15000 | K21: 7 | L21: 7 | M21: 7 | N21: =CHOOSE(Scenario,K21,L21,M21) -> 7 | P21: =IF(F21="Monthly",J21,IF(F21="Annual",J21/12,0)) -> 15000 | Q21: =IF(F21="One-time",IF(N21<=Horizon,J21,0),P21*MAX(0,MIN(Horizon,IF(O21="",Horizon,N21+O21-1))-N21+1)) -> 450000 | S21: Placeholder
A22: C19 | B22: Audit, tax, Form 990 support (affiliates billed separately) | C22: EnergyWave, Inc. | D22: Finance | E22: Audit & tax | F22: Annual | G22: 30000 | H22: 40000 | I22: 60000 | J22: =CHOOSE(Scenario,G22,H22,I22) -> 40000 | K22: 12 | L22: 12 | M22: 12 | N22: =CHOOSE(Scenario,K22,L22,M22) -> 12 | P22: =IF(F22="Monthly",J22,IF(F22="Annual",J22/12,0)) -> 3333.3333 | Q22: =IF(F22="One-time",IF(N22<=Horizon,J22,0),P22*MAX(0,MIN(Horizon,IF(O22="",Horizon,N22+O22-1))-N22+1)) -> 83333.333 | S22: Placeholder
A23: C20 | B23: Accounting / HR / cap-table systems (QuickBooks or NetSuite, payroll, Carta) | C23: EnergyWave, Inc. | D23: Finance | E23: Systems | F23: Monthly | G23: 800 | H23: 1500 | I23: 3000 | J23: =CHOOSE(Scenario,G23,H23,I23) -> 1500 | K23: 1 | L23: 1 | M23: 1 | N23: =CHOOSE(Scenario,K23,L23,M23) -> 1 | P23: =IF(F23="Monthly",J23,IF(F23="Annual",J23/12,0)) -> 1500 | Q23: =IF(F23="One-time",IF(N23<=Horizon,J23,0),P23*MAX(0,MIN(Horizon,IF(O23="",Horizon,N23+O23-1))-N23+1)) -> 54000 | S23: Placeholder
A24: C21 | B24: Insurance (D&O, GL, property, testing liability, workers' comp) | C24: EnergyWave, Inc. | D24: G&A | E24: Insurance | F24: Annual | G24: 60000 | H24: 90000 | I24: 140000 | J24: =CHOOSE(Scenario,G24,H24,I24) -> 90000 | K24: 1 | L24: 1 | M24: 1 | N24: =CHOOSE(Scenario,K24,L24,M24) -> 1 | P24: =IF(F24="Monthly",J24,IF(F24="Annual",J24/12,0)) -> 7500 | Q24: =IF(F24="One-time",IF(N24<=Horizon,J24,0),P24*MAX(0,MIN(Horizon,IF(O24="",Horizon,N24+O24-1))-N24+1)) -> 270000 | R24: Broker quote needed; lab operations drive the property/liability lines | S24: Placeholder
A25: C22 | B25: Recruiting — search fees, five applied physicists | C25: EnergyWave, Inc. | D25: G&A | E25: Recruiting | F25: One-time | G25: =RecruitFeePct*SUM(Headcount!$F$6:$F$10) -> 150000 | H25: =RecruitFeePct*SUM(Headcount!$F$6:$F$10) -> 150000 | I25: =RecruitFeePct*SUM(Headcount!$F$6:$F$10) -> 150000 | J25: =CHOOSE(Scenario,G25,H25,I25) -> 150000 | K25: 2 | L25: 1 | M25: 1 | N25: =CHOOSE(Scenario,K25,L25,M25) -> 1 | P25: =IF(F25="Monthly",J25,IF(F25="Annual",J25/12,0)) -> 0 | Q25: =IF(F25="One-time",IF(N25<=Horizon,J25,0),P25*MAX(0,MIN(Horizon,IF(O25="",Horizon,N25+O25-1))-N25+1)) -> 150000 | R25: Recruiting fee % × first-year base (H03–H07) | S25: Formula
A26: C23 | B26: Recruiting — other roles | C26: EnergyWave, Inc. | D26: G&A | E26: Recruiting | F26: One-time | G26: 30000 | H26: 50000 | I26: 80000 | J26: =CHOOSE(Scenario,G26,H26,I26) -> 50000 | K26: 2 | L26: 1 | M26: 1 | N26: =CHOOSE(Scenario,K26,L26,M26) -> 1 | P26: =IF(F26="Monthly",J26,IF(F26="Annual",J26/12,0)) -> 0 | Q26: =IF(F26="One-time",IF(N26<=Horizon,J26,0),P26*MAX(0,MIN(Horizon,IF(O26="",Horizon,N26+O26-1))-N26+1)) -> 50000 | S26: Placeholder
A27: C24 | B27: Travel & government engagement | C27: EnergyWave, Inc. | D27: G&A | E27: Travel | F27: Monthly | G27: 4000 | H27: 8000 | I27: 12000 | J27: =CHOOSE(Scenario,G27,H27,I27) -> 8000 | K27: 1 | L27: 1 | M27: 1 | N27: =CHOOSE(Scenario,K27,L27,M27) -> 1 | P27: =IF(F27="Monthly",J27,IF(F27="Annual",J27/12,0)) -> 8000 | Q27: =IF(F27="One-time",IF(N27<=Horizon,J27,0),P27*MAX(0,MIN(Horizon,IF(O27="",Horizon,N27+O27-1))-N27+1)) -> 288000 | S27: Placeholder
A28: C25 | B28: Publications, null-results registry, conferences | C28: EnergyWave, Inc. | D28: Research | E28: Dissemination | F28: Monthly | G28: 1500 | H28: 3000 | I28: 5000 | J28: =CHOOSE(Scenario,G28,H28,I28) -> 3000 | K28: 3 | L28: 2 | M28: 1 | N28: =CHOOSE(Scenario,K28,L28,M28) -> 2 | P28: =IF(F28="Monthly",J28,IF(F28="Annual",J28/12,0)) -> 3000 | Q28: =IF(F28="One-time",IF(N28<=Horizon,J28,0),P28*MAX(0,MIN(Horizon,IF(O28="",Horizon,N28+O28-1))-N28+1)) -> 105000 | S28: Placeholder
A29: C26 | B29: Office equipment & IT hardware | C29: EnergyWave, Inc. | D29: G&A | E29: Office | F29: One-time | G29: 40000 | H29: 70000 | I29: 120000 | J29: =CHOOSE(Scenario,G29,H29,I29) -> 70000 | K29: 3 | L29: 2 | M29: 1 | N29: =CHOOSE(Scenario,K29,L29,M29) -> 2 | P29: =IF(F29="Monthly",J29,IF(F29="Annual",J29/12,0)) -> 0 | Q29: =IF(F29="One-time",IF(N29<=Horizon,J29,0),P29*MAX(0,MIN(Horizon,IF(O29="",Horizon,N29+O29-1))-N29+1)) -> 70000 | S29: Placeholder
A30: C27 | B30: Intercompany services to/from GovThink Institute & pinnacle.blog (arms-length) | C30: EnergyWave, Inc. | D30: Intercompany | E30: Affiliates | F30: Monthly | G30: 0 | H30: 0 | I30: 0 | J30: =CHOOSE(Scenario,G30,H30,I30) -> 0 | K30: 1 | L30: 1 | M30: 1 | N30: =CHOOSE(Scenario,K30,L30,M30) -> 1 | P30: =IF(F30="Monthly",J30,IF(F30="Annual",J30/12,0)) -> 0 | Q30: =IF(F30="One-time",IF(N30<=Horizon,J30,0),P30*MAX(0,MIN(Horizon,IF(O30="",Horizon,N30+O30-1))-N30+1)) -> 0 | R30: BLOCKED — do not populate until Novak confirms structure; any services priced at FMV under written agreement | S30: Blocked
B31: Total (selected scenario, 36 months) | Q31: =SUM(Q4:Q30) -> 6620833.3

Sheet Monthly
A1: Monthly cash-need engine (36 months)
A2: Scenario: | B2: =ScenarioName -> Base | D2: All rows pull from Headcount and CostLines; edit inputs there, not here.
A4: Line | B4: Entity | C4: Category | D4: Subcategory | E4: 36-mo total ($) | F4: 1 | G4: 2 | H4: 3 | I4: 4 | J4: 5 | K4: 6 | L4: 7 | M4: 8 | N4: 9 | O4: 10 | P4: 11 | Q4: 12 | R4: 13 | S4: 14 | T4: 15 | U4: 16 | V4: 17 | W4: 18 | X4: 19 | Y4: 20 | Z4: 21 | AA4: 22 | AB4: 23 | AC4: 24 | AD4: 25 | AE4: 26 | AF4: 27 | AG4: 28 | AH4: 29 | AI4: 30 | AJ4: 31 | AK4: 32 | AL4: 33 | AM4: 34 | AN4: 35 | AO4: 36
E5: Month | F5: =EDATE(StartDate,F$4-1) -> 46388 | G5: =EDATE(StartDate,G$4-1) -> 46419 | H5: =EDATE(StartDate,H$4-1) -> 46447 | I5: =EDATE(StartDate,I$4-1) -> 46478 | J5: =EDATE(StartDate,J$4-1) -> 46508 | K5: =EDATE(StartDate,K$4-1) -> 46539 | L5: =EDATE(StartDate,L$4-1) -> 46569 | M5: =EDATE(StartDate,M$4-1) -> 46600 | ... AO5: =EDATE(StartDate,AO$4-1) -> 47453
E6: Gate | F6: =IF(F$4=Gate1,"G1",IF(F$4=Gate2,"G2",IF(F$4=Gate3,"G3",""))) | G6: =IF(G$4=Gate1,"G1",IF(G$4=Gate2,"G2",IF(G$4=Gate3,"G3",""))) | H6: =IF(H$4=Gate1,"G1",IF(H$4=Gate2,"G2",IF(H$4=Gate3,"G3",""))) | I6: =IF(I$4=Gate1,"G1",IF(I$4=Gate2,"G2",IF(I$4=Gate3,"G3",""))) | J6: =IF(J$4=Gate1,"G1",IF(J$4=Gate2,"G2",IF(J$4=Gate3,"G3",""))) | K6: =IF(K$4=Gate1,"G1",IF(K$4=Gate2,"G2",IF(K$4=Gate3,"G3",""))) | L6: =IF(L$4=Gate1,"G1",IF(L$4=Gate2,"G2",IF(L$4=Gate3,"G3",""))) | M6: =IF(M$4=Gate1,"G1",IF(M$4=Gate2,"G2",IF(M$4=Gate3,"G3",""))) | ... AO6: =IF(AO$4=Gate1,"G1",IF(AO$4=Gate2,"G2",IF(AO$4=Gate3,"G3",""))) -> G3
A7: PEOPLE (from Headcount)
A8: =Headcount!B4 -> Founder & CEO | B8: =Headcount!D4 -> EnergyWave, Inc. | C8: =IF(Headcount!E4="W-2","Payroll","Consulting") -> Payroll | D8: =IF(Headcount!E4="W-2","Salary & load","Consulting fee") -> Salary & load | E8: =SUM(F8:AO8) -> 878400 | F8: =IF(F$4>=Headcount!$M4,Headcount!$N4,0) -> 24400 | G8: =IF(G$4>=Headcount!$M4,Headcount!$N4,0) -> 24400 | H8: =IF(H$4>=Headcount!$M4,Headcount!$N4,0) -> 24400 | I8: =IF(I$4>=Headcount!$M4,Headcount!$N4,0) -> 24400 | J8: =IF(J$4>=Headcount!$M4,Headcount!$N4,0) -> 24400 | K8: =IF(K$4>=Headcount!$M4,Headcount!$N4,0) -> 24400 | L8: =IF(L$4>=Headcount!$M4,Headcount!$N4,0) -> 24400 | M8: =IF(M$4>=Headcount!$M4,Headcount!$N4,0) -> 24400 | ... AO8: =IF(AO$4>=Headcount!$M4,Headcount!$N4,0) -> 24400
A9: =Headcount!B5 -> Co-founder / Research Director (part-time) | B9: =Headcount!D5 -> EnergyWave, Inc. | C9: =IF(Headcount!E5="W-2","Payroll","Consulting") -> Consulting | D9: =IF(Headcount!E5="W-2","Salary & load","Consulting fee") -> Consulting fee | E9: =SUM(F9:AO9) -> 450000 | F9: =IF(F$4>=Headcount!$M5,Headcount!$N5,0) -> 12500 | G9: =IF(G$4>=Headcount!$M5,Headcount!$N5,0) -> 12500 | H9: =IF(H$4>=Headcount!$M5,Headcount!$N5,0) -> 12500 | I9: =IF(I$4>=Headcount!$M5,Headcount!$N5,0) -> 12500 | J9: =IF(J$4>=Headcount!$M5,Headcount!$N5,0) -> 12500 | K9: =IF(K$4>=Headcount!$M5,Headcount!$N5,0) -> 12500 | L9: =IF(L$4>=Headcount!$M5,Headcount!$N5,0) -> 12500 | M9: =IF(M$4>=Headcount!$M5,Headcount!$N5,0) -> 12500 | ... AO9: =IF(AO$4>=Headcount!$M5,Headcount!$N5,0) -> 12500
A10: =Headcount!B6 -> Applied Physicist 1 | B10: =Headcount!D6 -> EnergyWave, Inc. | C10: =IF(Headcount!E6="W-2","Payroll","Consulting") -> Payroll | D10: =IF(Headcount!E6="W-2","Salary & load","Consulting fee") -> Salary & load | E10: =SUM(F10:AO10) -> 533750 | F10: =IF(F$4>=Headcount!$M6,Headcount!$N6,0) -> 0 | G10: =IF(G$4>=Headcount!$M6,Headcount!$N6,0) -> 15250 | H10: =IF(H$4>=Headcount!$M6,Headcount!$N6,0) -> 15250 | I10: =IF(I$4>=Headcount!$M6,Headcount!$N6,0) -> 15250 | J10: =IF(J$4>=Headcount!$M6,Headcount!$N6,0) -> 15250 | K10: =IF(K$4>=Headcount!$M6,Headcount!$N6,0) -> 15250 | L10: =IF(L$4>=Headcount!$M6,Headcount!$N6,0) -> 15250 | M10: =IF(M$4>=Headcount!$M6,Headcount!$N6,0) -> 15250 | ... AO10: =IF(AO$4>=Headcount!$M6,Headcount!$N6,0) -> 15250
A11: =Headcount!B7 -> Applied Physicist 2 | B11: =Headcount!D7 -> EnergyWave, Inc. | C11: =IF(Headcount!E7="W-2","Payroll","Consulting") -> Payroll | D11: =IF(Headcount!E7="W-2","Salary & load","Consulting fee") -> Salary & load | E11: =SUM(F11:AO11) -> 533750 | F11: =IF(F$4>=Headcount!$M7,Headcount!$N7,0) -> 0 | G11: =IF(G$4>=Headcount!$M7,Headcount!$N7,0) -> 15250 | H11: =IF(H$4>=Headcount!$M7,Headcount!$N7,0) -> 15250 | I11: =IF(I$4>=Headcount!$M7,Headcount!$N7,0) -> 15250 | J11: =IF(J$4>=Headcount!$M7,Headcount!$N7,0) -> 15250 | K11: =IF(K$4>=Headcount!$M7,Headcount!$N7,0) -> 15250 | L11: =IF(L$4>=Headcount!$M7,Headcount!$N7,0) -> 15250 | M11: =IF(M$4>=Headcount!$M7,Headcount!$N7,0) -> 15250 | ... AO11: =IF(AO$4>=Headcount!$M7,Headcount!$N7,0) -> 15250
A12: =Headcount!B8 -> Applied Physicist 3 | B12: =Headcount!D8 -> EnergyWave, Inc. | C12: =IF(Headcount!E8="W-2","Payroll","Consulting") -> Payroll | D12: =IF(Headcount!E8="W-2","Salary & load","Consulting fee") -> Salary & load | E12: =SUM(F12:AO12) -> 518500 | F12: =IF(F$4>=Headcount!$M8,Headcount!$N8,0) -> 0 | G12: =IF(G$4>=Headcount!$M8,Headcount!$N8,0) -> 0 | H12: =IF(H$4>=Headcount!$M8,Headcount!$N8,0) -> 15250 | I12: =IF(I$4>=Headcount!$M8,Headcount!$N8,0) -> 15250 | J12: =IF(J$4>=Headcount!$M8,Headcount!$N8,0) -> 15250 | K12: =IF(K$4>=Headcount!$M8,Headcount!$N8,0) -> 15250 | L12: =IF(L$4>=Headcount!$M8,Headcount!$N8,0) -> 15250 | M12: =IF(M$4>=Headcount!$M8,Headcount!$N8,0) -> 15250 | ... AO12: =IF(AO$4>=Headcount!$M8,Headcount!$N8,0) -> 15250
A13: =Headcount!B9 -> Applied Physicist 4 | B13: =Headcount!D9 -> EnergyWave, Inc. | C13: =IF(Headcount!E9="W-2","Payroll","Consulting") -> Payroll | D13: =IF(Headcount!E9="W-2","Salary & load","Consulting fee") -> Salary & load | E13: =SUM(F13:AO13) -> 503250 | F13: =IF(F$4>=Headcount!$M9,Headcount!$N9,0) -> 0 | G13: =IF(G$4>=Headcount!$M9,Headcount!$N9,0) -> 0 | H13: =IF(H$4>=Headcount!$M9,Headcount!$N9,0) -> 0 | I13: =IF(I$4>=Headcount!$M9,Headcount!$N9,0) -> 15250 | J13: =IF(J$4>=Headcount!$M9,Headcount!$N9,0) -> 15250 | K13: =IF(K$4>=Headcount!$M9,Headcount!$N9,0) -> 15250 | L13: =IF(L$4>=Headcount!$M9,Headcount!$N9,0) -> 15250 | M13: =IF(M$4>=Headcount!$M9,Headcount!$N9,0) -> 15250 | ... AO13: =IF(AO$4>=Headcount!$M9,Headcount!$N9,0) -> 15250
A14: =Headcount!B10 -> Applied Physicist 5 | B14: =Headcount!D10 -> EnergyWave, Inc. | C14: =IF(Headcount!E10="W-2","Payroll","Consulting") -> Payroll | D14: =IF(Headcount!E10="W-2","Salary & load","Consulting fee") -> Salary & load | E14: =SUM(F14:AO14) -> 488000 | F14: =IF(F$4>=Headcount!$M10,Headcount!$N10,0) -> 0 | G14: =IF(G$4>=Headcount!$M10,Headcount!$N10,0) -> 0 | H14: =IF(H$4>=Headcount!$M10,Headcount!$N10,0) -> 0 | I14: =IF(I$4>=Headcount!$M10,Headcount!$N10,0) -> 0 | J14: =IF(J$4>=Headcount!$M10,Headcount!$N10,0) -> 15250 | K14: =IF(K$4>=Headcount!$M10,Headcount!$N10,0) -> 15250 | L14: =IF(L$4>=Headcount!$M10,Headcount!$N10,0) -> 15250 | M14: =IF(M$4>=Headcount!$M10,Headcount!$N10,0) -> 15250 | ... AO14: =IF(AO$4>=Headcount!$M10,Headcount!$N10,0) -> 15250
A15: =Headcount!B11 -> Theoretical Physicist — consulting agreement 1 | B15: =Headcount!D11 -> EnergyWave, Inc. | C15: =IF(Headcount!E11="W-2","Payroll","Consulting") -> Consulting | D15: =IF(Headcount!E11="W-2","Salary & load","Consulting fee") -> Consulting fee | E15: =SUM(F15:AO15) -> 1500000 | F15: =IF(F$4>=Headcount!$M11,Headcount!$N11,0) -> 41666.667 | G15: =IF(G$4>=Headcount!$M11,Headcount!$N11,0) -> 41666.667 | H15: =IF(H$4>=Headcount!$M11,Headcount!$N11,0) -> 41666.667 | I15: =IF(I$4>=Headcount!$M11,Headcount!$N11,0) -> 41666.667 | J15: =IF(J$4>=Headcount!$M11,Headcount!$N11,0) -> 41666.667 | K15: =IF(K$4>=Headcount!$M11,Headcount!$N11,0) -> 41666.667 | L15: =IF(L$4>=Headcount!$M11,Headcount!$N11,0) -> 41666.667 | M15: =IF(M$4>=Headcount!$M11,Headcount!$N11,0) -> 41666.667 | ... AO15: =IF(AO$4>=Headcount!$M11,Headcount!$N11,0) -> 41666.667
A16: =Headcount!B12 -> Theoretical Physicist — consulting agreement 2 | B16: =Headcount!D12 -> EnergyWave, Inc. | C16: =IF(Headcount!E12="W-2","Payroll","Consulting") -> Consulting | D16: =IF(Headcount!E12="W-2","Salary & load","Consulting fee") -> Consulting fee | E16: =SUM(F16:AO16) -> 1416666.7 | F16: =IF(F$4>=Headcount!$M12,Headcount!$N12,0) -> 0 | G16: =IF(G$4>=Headcount!$M12,Headcount!$N12,0) -> 0 | H16: =IF(H$4>=Headcount!$M12,Headcount!$N12,0) -> 41666.667 | I16: =IF(I$4>=Headcount!$M12,Headcount!$N12,0) -> 41666.667 | J16: =IF(J$4>=Headcount!$M12,Headcount!$N12,0) -> 41666.667 | K16: =IF(K$4>=Headcount!$M12,Headcount!$N12,0) -> 41666.667 | L16: =IF(L$4>=Headcount!$M12,Headcount!$N12,0) -> 41666.667 | M16: =IF(M$4>=Headcount!$M12,Headcount!$N12,0) -> 41666.667 | ... AO16: =IF(AO$4>=Headcount!$M12,Headcount!$N12,0) -> 41666.667
A17: =Headcount!B13 -> Lab Safety / EHS Officer | B17: =Headcount!D13 -> EnergyWave, Inc. | C17: =IF(Headcount!E13="W-2","Payroll","Consulting") -> Payroll | D17: =IF(Headcount!E13="W-2","Salary & load","Consulting fee") -> Salary & load | E17: =SUM(F17:AO17) -> 439200 | F17: =IF(F$4>=Headcount!$M13,Headcount!$N13,0) -> 12200 | G17: =IF(G$4>=Headcount!$M13,Headcount!$N13,0) -> 12200 | H17: =IF(H$4>=Headcount!$M13,Headcount!$N13,0) -> 12200 | I17: =IF(I$4>=Headcount!$M13,Headcount!$N13,0) -> 12200 | J17: =IF(J$4>=Headcount!$M13,Headcount!$N13,0) -> 12200 | K17: =IF(K$4>=Headcount!$M13,Headcount!$N13,0) -> 12200 | L17: =IF(L$4>=Headcount!$M13,Headcount!$N13,0) -> 12200 | M17: =IF(M$4>=Headcount!$M13,Headcount!$N13,0) -> 12200 | ... AO17: =IF(AO$4>=Headcount!$M13,Headcount!$N13,0) -> 12200
A18: =Headcount!B14 -> Test & Instrumentation Engineer 1 (calorimetry) | B18: =Headcount!D14 -> EnergyWave, Inc. | C18: =IF(Headcount!E14="W-2","Payroll","Consulting") -> Payroll | D18: =IF(Headcount!E14="W-2","Salary & load","Consulting fee") -> Salary & load | E18: =SUM(F18:AO18) -> 480375 | F18: =IF(F$4>=Headcount!$M14,Headcount!$N14,0) -> 0 | G18: =IF(G$4>=Headcount!$M14,Headcount!$N14,0) -> 13725 | H18: =IF(H$4>=Headcount!$M14,Headcount!$N14,0) -> 13725 | I18: =IF(I$4>=Headcount!$M14,Headcount!$N14,0) -> 13725 | J18: =IF(J$4>=Headcount!$M14,Headcount!$N14,0) -> 13725 | K18: =IF(K$4>=Headcount!$M14,Headcount!$N14,0) -> 13725 | L18: =IF(L$4>=Headcount!$M14,Headcount!$N14,0) -> 13725 | M18: =IF(M$4>=Headcount!$M14,Headcount!$N14,0) -> 13725 | ... AO18: =IF(AO$4>=Headcount!$M14,Headcount!$N14,0) -> 13725
A19: =Headcount!B15 -> Test & Instrumentation Engineer 2 | B19: =Headcount!D15 -> EnergyWave, Inc. | C19: =IF(Headcount!E15="W-2","Payroll","Consulting") -> Payroll | D19: =IF(Headcount!E15="W-2","Salary & load","Consulting fee") -> Salary & load | E19: =SUM(F19:AO19) -> 452925 | F19: =IF(F$4>=Headcount!$M15,Headcount!$N15,0) -> 0 | G19: =IF(G$4>=Headcount!$M15,Headcount!$N15,0) -> 0 | H19: =IF(H$4>=Headcount!$M15,Headcount!$N15,0) -> 0 | I19: =IF(I$4>=Headcount!$M15,Headcount!$N15,0) -> 13725 | J19: =IF(J$4>=Headcount!$M15,Headcount!$N15,0) -> 13725 | K19: =IF(K$4>=Headcount!$M15,Headcount!$N15,0) -> 13725 | L19: =IF(L$4>=Headcount!$M15,Headcount!$N15,0) -> 13725 | M19: =IF(M$4>=Headcount!$M15,Headcount!$N15,0) -> 13725 | ... AO19: =IF(AO$4>=Headcount!$M15,Headcount!$N15,0) -> 13725
... A25: =Headcount!B21 -> Government Liaison (consulting) | B25: =Headcount!D21 -> EnergyWave, Inc. | C25: =IF(Headcount!E21="W-2","Payroll","Consulting") -> Consulting | D25: =IF(Headcount!E21="W-2","Salary & load","Consulting fee") -> Consulting fee | E25: =SUM(F25:AO25) -> 180000 | F25: =IF(F$4>=Headcount!$M21,Headcount!$N21,0) -> 5000 | G25: =IF(G$4>=Headcount!$M21,Headcount!$N21,0) -> 5000 | H25: =IF(H$4>=Headcount!$M21,Headcount!$N21,0) -> 5000 | I25: =IF(I$4>=Headcount!$M21,Headcount!$N21,0) -> 5000 | J25: =IF(J$4>=Headcount!$M21,Headcount!$N21,0) -> 5000 | K25: =IF(K$4>=Headcount!$M21,Headcount!$N21,0) -> 5000 | L25: =IF(L$4>=Headcount!$M21,Headcount!$N21,0) -> 5000 | M25: =IF(M$4>=Headcount!$M21,Headcount!$N21,0) -> 5000 | ... AO25: =IF(AO$4>=Headcount!$M21,Headcount!$N21,0) -> 5000
A26: Relocation (one-time, all hires) | B26: EnergyWave, Inc. | C26: Payroll | D26: Relocation | E26: =SUM(F26:AO26) -> 195000 | F26: =SUMPRODUCT((Headcount!$M$4:$M$21=F$4)*Headcount!$H$4:$H$21) -> 10000 | G26: =SUMPRODUCT((Headcount!$M$4:$M$21=G$4)*Headcount!$H$4:$H$21) -> 65000 | H26: =SUMPRODUCT((Headcount!$M$4:$M$21=H$4)*Headcount!$H$4:$H$21) -> 55000 | I26: =SUMPRODUCT((Headcount!$M$4:$M$21=I$4)*Headcount!$H$4:$H$21) -> 40000 | J26: =SUMPRODUCT((Headcount!$M$4:$M$21=J$4)*Headcount!$H$4:$H$21) -> 25000 | K26: =SUMPRODUCT((Headcount!$M$4:$M$21=K$4)*Headcount!$H$4:$H$21) -> 0 | L26: =SUMPRODUCT((Headcount!$M$4:$M$21=L$4)*Headcount!$H$4:$H$21) -> 0 | M26: =SUMPRODUCT((Headcount!$M$4:$M$21=M$4)*Headcount!$H$4:$H$21) -> 0 | ... AO26: =SUMPRODUCT((Headcount!$M$4:$M$21=AO$4)*Headcount!$H$4:$H$21) -> 0
A27: NON-PAYROLL (from CostLines)
A28: =CostLines!B4 -> Office + lab lease near UCI (University Research Park) | B28: =CostLines!C4 -> EnergyWave, Inc. | C28: =CostLines!D4 -> Facilities | D28: =CostLines!E4 -> Lease | E28: =SUM(F28:AO28) -> 787500 | F28: =IF(CostLines!$F4="One-time",IF(F$4=CostLines!$N4,CostLines!$J4,0),IF(AND(F$4>=CostLines!$N4,IF(CostLines!$O4="",TRUE(),F$4<CostLines!$N4+CostLines!$O4)),CostLines!$P4,0)) -> 0 | G28: =IF(CostLines!$F4="One-time",IF(G$4=CostLines!$N4,CostLines!$J4,0),IF(AND(G$4>=CostLines!$N4,IF(CostLines!$O4="",TRUE(),G$4<CostLines!$N4+CostLines!$O4)),CostLines!$P4,0)) -> 22500 | H28: =IF(CostLines!$F4="One-time",IF(H$4=CostLines!$N4,CostLines!$J4,0),IF(AND(H$4>=CostLines!$N4,IF(CostLines!$O4="",TRUE(),H$4<CostLines!$N4+CostLines!$O4)),CostLines!$P4,0)) -> 22500 | I28: =IF(CostLines!$F4="One-time",IF(I$4=CostLines!$N4,CostLines!$J4,0),IF(AND(I$4>=CostLines!$N4,IF(CostLines!$O4="",TRUE(),I$4<CostLines!$N4+CostLines!$O4)),CostLines!$P4,0)) -> 22500 | J28: =IF(CostLines!$F4="One-time",IF(J$4=CostLines!$N4,CostLines!$J4,0),IF(AND(J$4>=CostLines!$N4,IF(CostLines!$O4="",TRUE(),J$4<CostLines!$N4+CostLines!$O4)),CostLines!$P4,0)) -> 22500 | K28: =IF(CostLines!$F4="One-time",IF(K$4=CostLines!$N4,CostLines!$J4,0),IF(AND(K$4>=CostLines!$N4,IF(CostLines!$O4="",TRUE(),K$4<CostLines!$N4+CostLines!$O4)),CostLines!$P4,0)) -> 22500 | L28: =IF(CostLines!$F4="One-time",IF(L$4=CostLines!$N4,CostLines!$J4,0),IF(AND(L$4>=CostLines!$N4,IF(CostLines!$O4="",TRUE(),L$4<CostLines!$N4+CostLines!$O4)),CostLines!$P4,0)) -> 22500 | M28: =IF(CostLines!$F4="One-time",IF(M$4=CostLines!$N4,CostLines!$J4,0),IF(AND(M$4>=CostLines!$N4,IF(CostLines!$O4="",TRUE(),M$4<CostLines!$N4+CostLines!$O4)),CostLines!$P4,0)) -> 22500 | ... AO28: =IF(CostLines!$F4="One-time",IF(AO$4=CostLines!$N4,CostLines!$J4,0),IF(AND(AO$4>=CostLines!$N4,IF(CostLines!$O4="",TRUE(),AO$4<CostLines!$N4+CostLines!$O4)),CostLines!$P4,0)) -> 22500
A29: =CostLines!B5 -> Security deposit | B29: =CostLines!C5 -> EnergyWave, Inc. | C29: =CostLines!D5 -> Facilities | D29: =CostLines!E5 -> Deposit | E29: =SUM(F29:AO29) -> 45000 | F29: =IF(CostLines!$F5="One-time",IF(F$4=CostLines!$N5,CostLines!$J5,0),IF(AND(F$4>=CostLines!$N5,IF(CostLines!$O5="",TRUE(),F$4<CostLines!$N5+CostLines!$O5)),CostLines!$P5,0)) -> 0 | G29: =IF(CostLines!$F5="One-time",IF(G$4=CostLines!$N5,CostLines!$J5,0),IF(AND(G$4>=CostLines!$N5,IF(CostLines!$O5="",TRUE(),G$4<CostLines!$N5+CostLines!$O5)),CostLines!$P5,0)) -> 45000 | H29: =IF(CostLines!$F5="One-time",IF(H$4=CostLines!$N5,CostLines!$J5,0),IF(AND(H$4>=CostLines!$N5,IF(CostLines!$O5="",TRUE(),H$4<CostLines!$N5+CostLines!$O5)),CostLines!$P5,0)) -> 0 | I29: =IF(CostLines!$F5="One-time",IF(I$4=CostLines!$N5,CostLines!$J5,0),IF(AND(I$4>=CostLines!$N5,IF(CostLines!$O5="",TRUE(),I$4<CostLines!$N5+CostLines!$O5)),CostLines!$P5,0)) -> 0 | J29: =IF(CostLines!$F5="One-time",IF(J$4=CostLines!$N5,CostLines!$J5,0),IF(AND(J$4>=CostLines!$N5,IF(CostLines!$O5="",TRUE(),J$4<CostLines!$N5+CostLines!$O5)),CostLines!$P5,0)) -> 0 | K29: =IF(CostLines!$F5="One-time",IF(K$4=CostLines!$N5,CostLines!$J5,0),IF(AND(K$4>=CostLines!$N5,IF(CostLines!$O5="",TRUE(),K$4<CostLines!$N5+CostLines!$O5)),CostLines!$P5,0)) -> 0 | L29: =IF(CostLines!$F5="One-time",IF(L$4=CostLines!$N5,CostLines!$J5,0),IF(AND(L$4>=CostLines!$N5,IF(CostLines!$O5="",TRUE(),L$4<CostLines!$N5+CostLines!$O5)),CostLines!$P5,0)) -> 0 | M29: =IF(CostLines!$F5="One-time",IF(M$4=CostLines!$N5,CostLines!$J5,0),IF(AND(M$4>=CostLines!$N5,IF(CostLines!$O5="",TRUE(),M$4<CostLines!$N5+CostLines!$O5)),CostLines!$P5,0)) -> 0 | ... AO29: =IF(CostLines!$F5="One-time",IF(AO$4=CostLines!$N5,CostLines!$J5,0),IF(AND(AO$4>=CostLines!$N5,IF(CostLines!$O5="",TRUE(),AO$4<CostLines!$N5+CostLines!$O5)),CostLines!$P5,0)) -> 0
A30: =CostLines!B6 -> Lab build-out (power, ventilation, benches, shielding) | B30: =CostLines!C6 -> EnergyWave, Inc. | C30: =CostLines!D6 -> Facilities | D30: =CostLines!E6 -> Build-out | E30: =SUM(F30:AO30) -> 300000 | F30: =IF(CostLines!$F6="One-time",IF(F$4=CostLines!$N6,CostLines!$J6,0),IF(AND(F$4>=CostLines!$N6,IF(CostLines!$O6="",TRUE(),F$4<CostLines!$N6+CostLines!$O6)),CostLines!$P6,0)) -> 0 | G30: =IF(CostLines!$F6="One-time",IF(G$4=CostLines!$N6,CostLines!$J6,0),IF(AND(G$4>=CostLines!$N6,IF(CostLines!$O6="",TRUE(),G$4<CostLines!$N6+CostLines!$O6)),CostLines!$P6,0)) -> 300000 | H30: =IF(CostLines!$F6="One-time",IF(H$4=CostLines!$N6,CostLines!$J6,0),IF(AND(H$4>=CostLines!$N6,IF(CostLines!$O6="",TRUE(),H$4<CostLines!$N6+CostLines!$O6)),CostLines!$P6,0)) -> 0 | I30: =IF(CostLines!$F6="One-time",IF(I$4=CostLines!$N6,CostLines!$J6,0),IF(AND(I$4>=CostLines!$N6,IF(CostLines!$O6="",TRUE(),I$4<CostLines!$N6+CostLines!$O6)),CostLines!$P6,0)) -> 0 | J30: =IF(CostLines!$F6="One-time",IF(J$4=CostLines!$N6,CostLines!$J6,0),IF(AND(J$4>=CostLines!$N6,IF(CostLines!$O6="",TRUE(),J$4<CostLines!$N6+CostLines!$O6)),CostLines!$P6,0)) -> 0 | K30: =IF(CostLines!$F6="One-time",IF(K$4=CostLines!$N6,CostLines!$J6,0),IF(AND(K$4>=CostLines!$N6,IF(CostLines!$O6="",TRUE(),K$4<CostLines!$N6+CostLines!$O6)),CostLines!$P6,0)) -> 0 | L30: =IF(CostLines!$F6="One-time",IF(L$4=CostLines!$N6,CostLines!$J6,0),IF(AND(L$4>=CostLines!$N6,IF(CostLines!$O6="",TRUE(),L$4<CostLines!$N6+CostLines!$O6)),CostLines!$P6,0)) -> 0 | M30: =IF(CostLines!$F6="One-time",IF(M$4=CostLines!$N6,CostLines!$J6,0),IF(AND(M$4>=CostLines!$N6,IF(CostLines!$O6="",TRUE(),M$4<CostLines!$N6+CostLines!$O6)),CostLines!$P6,0)) -> 0 | ... AO30: =IF(CostLines!$F6="One-time",IF(AO$4=CostLines!$N6,CostLines!$J6,0),IF(AND(AO$4>=CostLines!$N6,IF(CostLines!$O6="",TRUE(),AO$4<CostLines!$N6+CostLines!$O6)),CostLines!$P6,0)) -> 0
A31: =CostLines!B7 -> Utilities, internet, security | B31: =CostLines!C7 -> EnergyWave, Inc. | C31: =CostLines!D7 -> Facilities | D31: =CostLines!E7 -> Utilities | E31: =SUM(F31:AO31) -> 140000 | F31: =IF(CostLines!$F7="One-time",IF(F$4=CostLines!$N7,CostLines!$J7,0),IF(AND(F$4>=CostLines!$N7,IF(CostLines!$O7="",TRUE(),F$4<CostLines!$N7+CostLines!$O7)),CostLines!$P7,0)) -> 0 | G31: =IF(CostLines!$F7="One-time",IF(G$4=CostLines!$N7,CostLines!$J7,0),IF(AND(G$4>=CostLines!$N7,IF(CostLines!$O7="",TRUE(),G$4<CostLines!$N7+CostLines!$O7)),CostLines!$P7,0)) -> 4000 | H31: =IF(CostLines!$F7="One-time",IF(H$4=CostLines!$N7,CostLines!$J7,0),IF(AND(H$4>=CostLines!$N7,IF(CostLines!$O7="",TRUE(),H$4<CostLines!$N7+CostLines!$O7)),CostLines!$P7,0)) -> 4000 | I31: =IF(CostLines!$F7="One-time",IF(I$4=CostLines!$N7,CostLines!$J7,0),IF(AND(I$4>=CostLines!$N7,IF(CostLines!$O7="",TRUE(),I$4<CostLines!$N7+CostLines!$O7)),CostLines!$P7,0)) -> 4000 | J31: =IF(CostLines!$F7="One-time",IF(J$4=CostLines!$N7,CostLines!$J7,0),IF(AND(J$4>=CostLines!$N7,IF(CostLines!$O7="",TRUE(),J$4<CostLines!$N7+CostLines!$O7)),CostLines!$P7,0)) -> 4000 | K31: =IF(CostLines!$F7="One-time",IF(K$4=CostLines!$N7,CostLines!$J7,0),IF(AND(K$4>=CostLines!$N7,IF(CostLines!$O7="",TRUE(),K$4<CostLines!$N7+CostLines!$O7)),CostLines!$P7,0)) -> 4000 | L31: =IF(CostLines!$F7="One-time",IF(L$4=CostLines!$N7,CostLines!$J7,0),IF(AND(L$4>=CostLines!$N7,IF(CostLines!$O7="",TRUE(),L$4<CostLines!$N7+CostLines!$O7)),CostLines!$P7,0)) -> 4000 | M31: =IF(CostLines!$F7="One-time",IF(M$4=CostLines!$N7,CostLines!$J7,0),IF(AND(M$4>=CostLines!$N7,IF(CostLines!$O7="",TRUE(),M$4<CostLines!$N7+CostLines!$O7)),CostLines!$P7,0)) -> 4000 | ... AO31: =IF(CostLines!$F7="One-time",IF(AO$4=CostLines!$N7,CostLines!$J7,0),IF(AND(AO$4>=CostLines!$N7,IF(CostLines!$O7="",TRUE(),AO$4<CostLines!$N7+CostLines!$O7)),CostLines!$P7,0)) -> 4000
A32: =CostLines!B8 -> Tabletop instrumentation package (calorimeters, power analyzers, precision sources/loads, DAQ, thermal chambers, balances, shielded enclosure, reference standards) | B32: =CostLines!C8 -> EnergyWave, Inc. | C32: =CostLines!D8 -> Equipment | D32: =CostLines!E8 -> Instrumentation | E32: =SUM(F32:AO32) -> 450000 | F32: =IF(CostLines!$F8="One-time",IF(F$4=CostLines!$N8,CostLines!$J8,0),IF(AND(F$4>=CostLines!$N8,IF(CostLines!$O8="",TRUE(),F$4<CostLines!$N8+CostLines!$O8)),CostLines!$P8,0)) -> 0 | G32: =IF(CostLines!$F8="One-time",IF(G$4=CostLines!$N8,CostLines!$J8,0),IF(AND(G$4>=CostLines!$N8,IF(CostLines!$O8="",TRUE(),G$4<CostLines!$N8+CostLines!$O8)),CostLines!$P8,0)) -> 450000 | H32: =IF(CostLines!$F8="One-time",IF(H$4=CostLines!$N8,CostLines!$J8,0),IF(AND(H$4>=CostLines!$N8,IF(CostLines!$O8="",TRUE(),H$4<CostLines!$N8+CostLines!$O8)),CostLines!$P8,0)) -> 0 | I32: =IF(CostLines!$F8="One-time",IF(I$4=CostLines!$N8,CostLines!$J8,0),IF(AND(I$4>=CostLines!$N8,IF(CostLines!$O8="",TRUE(),I$4<CostLines!$N8+CostLines!$O8)),CostLines!$P8,0)) -> 0 | J32: =IF(CostLines!$F8="One-time",IF(J$4=CostLines!$N8,CostLines!$J8,0),IF(AND(J$4>=CostLines!$N8,IF(CostLines!$O8="",TRUE(),J$4<CostLines!$N8+CostLines!$O8)),CostLines!$P8,0)) -> 0 | K32: =IF(CostLines!$F8="One-time",IF(K$4=CostLines!$N8,CostLines!$J8,0),IF(AND(K$4>=CostLines!$N8,IF(CostLines!$O8="",TRUE(),K$4<CostLines!$N8+CostLines!$O8)),CostLines!$P8,0)) -> 0 | L32: =IF(CostLines!$F8="One-time",IF(L$4=CostLines!$N8,CostLines!$J8,0),IF(AND(L$4>=CostLines!$N8,IF(CostLines!$O8="",TRUE(),L$4<CostLines!$N8+CostLines!$O8)),CostLines!$P8,0)) -> 0 | M32: =IF(CostLines!$F8="One-time",IF(M$4=CostLines!$N8,CostLines!$J8,0),IF(AND(M$4>=CostLines!$N8,IF(CostLines!$O8="",TRUE(),M$4<CostLines!$N8+CostLines!$O8)),CostLines!$P8,0)) -> 0 | ... AO32: =IF(CostLines!$F8="One-time",IF(AO$4=CostLines!$N8,CostLines!$J8,0),IF(AND(AO$4>=CostLines!$N8,IF(CostLines!$O8="",TRUE(),AO$4<CostLines!$N8+CostLines!$O8)),CostLines!$P8,0)) -> 0
A33: =CostLines!B9 -> Calibration & metrology services | B33: =CostLines!C9 -> EnergyWave, Inc. | C33: =CostLines!D9 -> Equipment | D33: =CostLines!E9 -> Calibration | E33: =SUM(F33:AO33) -> 85000 | F33: =IF(CostLines!$F9="One-time",IF(F$4=CostLines!$N9,CostLines!$J9,0),IF(AND(F$4>=CostLines!$N9,IF(CostLines!$O9="",TRUE(),F$4<CostLines!$N9+CostLines!$O9)),CostLines!$P9,0)) -> 0 | G33: =IF(CostLines!$F9="One-time",IF(G$4=CostLines!$N9,CostLines!$J9,0),IF(AND(G$4>=CostLines!$N9,IF(CostLines!$O9="",TRUE(),G$4<CostLines!$N9+CostLines!$O9)),CostLines!$P9,0)) -> 0 | H33: =IF(CostLines!$F9="One-time",IF(H$4=CostLines!$N9,CostLines!$J9,0),IF(AND(H$4>=CostLines!$N9,IF(CostLines!$O9="",TRUE(),H$4<CostLines!$N9+CostLines!$O9)),CostLines!$P9,0)) -> 2500 | I33: =IF(CostLines!$F9="One-time",IF(I$4=CostLines!$N9,CostLines!$J9,0),IF(AND(I$4>=CostLines!$N9,IF(CostLines!$O9="",TRUE(),I$4<CostLines!$N9+CostLines!$O9)),CostLines!$P9,0)) -> 2500 | J33: =IF(CostLines!$F9="One-time",IF(J$4=CostLines!$N9,CostLines!$J9,0),IF(AND(J$4>=CostLines!$N9,IF(CostLines!$O9="",TRUE(),J$4<CostLines!$N9+CostLines!$O9)),CostLines!$P9,0)) -> 2500 | K33: =IF(CostLines!$F9="One-time",IF(K$4=CostLines!$N9,CostLines!$J9,0),IF(AND(K$4>=CostLines!$N9,IF(CostLines!$O9="",TRUE(),K$4<CostLines!$N9+CostLines!$O9)),CostLines!$P9,0)) -> 2500 | L33: =IF(CostLines!$F9="One-time",IF(L$4=CostLines!$N9,CostLines!$J9,0),IF(AND(L$4>=CostLines!$N9,IF(CostLines!$O9="",TRUE(),L$4<CostLines!$N9+CostLines!$O9)),CostLines!$P9,0)) -> 2500 | M33: =IF(CostLines!$F9="One-time",IF(M$4=CostLines!$N9,CostLines!$J9,0),IF(AND(M$4>=CostLines!$N9,IF(CostLines!$O9="",TRUE(),M$4<CostLines!$N9+CostLines!$O9)),CostLines!$P9,0)) -> 2500 | ... AO33: =IF(CostLines!$F9="One-time",IF(AO$4=CostLines!$N9,CostLines!$J9,0),IF(AND(AO$4>=CostLines!$N9,IF(CostLines!$O9="",TRUE(),AO$4<CostLines!$N9+CostLines!$O9)),CostLines!$P9,0)) -> 2500
A34: =CostLines!B10 -> Precision additive-manufacturing system (high-resolution AM with closed-loop process control) | B34: =CostLines!C10 -> EnergyWave, Inc. | C34: =CostLines!D10 -> Equipment | D34: =CostLines!E10 -> Additive manufacturing | E34: =SUM(F34:AO34) -> 750000 | F34: =IF(CostLines!$F10="One-time",IF(F$4=CostLines!$N10,CostLines!$J10,0),IF(AND(F$4>=CostLines!$N10,IF(CostLines!$O10="",TRUE(),F$4<CostLines!$N10+CostLines!$O10)),CostLines!$P10,0)) -> 0 | G34: =IF(CostLines!$F10="One-time",IF(G$4=CostLines!$N10,CostLines!$J10,0),IF(AND(G$4>=CostLines!$N10,IF(CostLines!$O10="",TRUE(),G$4<CostLines!$N10+CostLines!$O10)),CostLines!$P10,0)) -> 0 | H34: =IF(CostLines!$F10="One-time",IF(H$4=CostLines!$N10,CostLines!$J10,0),IF(AND(H$4>=CostLines!$N10,IF(CostLines!$O10="",TRUE(),H$4<CostLines!$N10+CostLines!$O10)),CostLines!$P10,0)) -> 750000 | I34: =IF(CostLines!$F10="One-time",IF(I$4=CostLines!$N10,CostLines!$J10,0),IF(AND(I$4>=CostLines!$N10,IF(CostLines!$O10="",TRUE(),I$4<CostLines!$N10+CostLines!$O10)),CostLines!$P10,0)) -> 0 | J34: =IF(CostLines!$F10="One-time",IF(J$4=CostLines!$N10,CostLines!$J10,0),IF(AND(J$4>=CostLines!$N10,IF(CostLines!$O10="",TRUE(),J$4<CostLines!$N10+CostLines!$O10)),CostLines!$P10,0)) -> 0 | K34: =IF(CostLines!$F10="One-time",IF(K$4=CostLines!$N10,CostLines!$J10,0),IF(AND(K$4>=CostLines!$N10,IF(CostLines!$O10="",TRUE(),K$4<CostLines!$N10+CostLines!$O10)),CostLines!$P10,0)) -> 0 | L34: =IF(CostLines!$F10="One-time",IF(L$4=CostLines!$N10,CostLines!$J10,0),IF(AND(L$4>=CostLines!$N10,IF(CostLines!$O10="",TRUE(),L$4<CostLines!$N10+CostLines!$O10)),CostLines!$P10,0)) -> 0 | M34: =IF(CostLines!$F10="One-time",IF(M$4=CostLines!$N10,CostLines!$J10,0),IF(AND(M$4>=CostLines!$N10,IF(CostLines!$O10="",TRUE(),M$4<CostLines!$N10+CostLines!$O10)),CostLines!$P10,0)) -> 0 | ... AO34: =IF(CostLines!$F10="One-time",IF(AO$4=CostLines!$N10,CostLines!$J10,0),IF(AND(AO$4>=CostLines!$N10,IF(CostLines!$O10="",TRUE(),AO$4<CostLines!$N10+CostLines!$O10)),CostLines!$P10,0)) -> 0
A35: =CostLines!B11 -> AM service contract & software | B35: =CostLines!C11 -> EnergyWave, Inc. | C35: =CostLines!D11 -> Equipment | D35: =CostLines!E11 -> Additive manufacturing | E35: =SUM(F35:AO35) -> 110000 | F35: =IF(CostLines!$F11="One-time",IF(F$4=CostLines!$N11,CostLines!$J11,0),IF(AND(F$4>=CostLines!$N11,IF(CostLines!$O11="",TRUE(),F$4<CostLines!$N11+CostLines!$O11)),CostLines!$P11,0)) -> 0 | G35: =IF(CostLines!$F11="One-time",IF(G$4=CostLines!$N11,CostLines!$J11,0),IF(AND(G$4>=CostLines!$N11,IF(CostLines!$O11="",TRUE(),G$4<CostLines!$N11+CostLines!$O11)),CostLines!$P11,0)) -> 0 | H35: =IF(CostLines!$F11="One-time",IF(H$4=CostLines!$N11,CostLines!$J11,0),IF(AND(H$4>=CostLines!$N11,IF(CostLines!$O11="",TRUE(),H$4<CostLines!$N11+CostLines!$O11)),CostLines!$P11,0)) -> 0 | I35: =IF(CostLines!$F11="One-time",IF(I$4=CostLines!$N11,CostLines!$J11,0),IF(AND(I$4>=CostLines!$N11,IF(CostLines!$O11="",TRUE(),I$4<CostLines!$N11+CostLines!$O11)),CostLines!$P11,0)) -> 3333.3333 | J35: =IF(CostLines!$F11="One-time",IF(J$4=CostLines!$N11,CostLines!$J11,0),IF(AND(J$4>=CostLines!$N11,IF(CostLines!$O11="",TRUE(),J$4<CostLines!$N11+CostLines!$O11)),CostLines!$P11,0)) -> 3333.3333 | K35: =IF(CostLines!$F11="One-time",IF(K$4=CostLines!$N11,CostLines!$J11,0),IF(AND(K$4>=CostLines!$N11,IF(CostLines!$O11="",TRUE(),K$4<CostLines!$N11+CostLines!$O11)),CostLines!$P11,0)) -> 3333.3333 | L35: =IF(CostLines!$F11="One-time",IF(L$4=CostLines!$N11,CostLines!$J11,0),IF(AND(L$4>=CostLines!$N11,IF(CostLines!$O11="",TRUE(),L$4<CostLines!$N11+CostLines!$O11)),CostLines!$P11,0)) -> 3333.3333 | M35: =IF(CostLines!$F11="One-time",IF(M$4=CostLines!$N11,CostLines!$J11,0),IF(AND(M$4>=CostLines!$N11,IF(CostLines!$O11="",TRUE(),M$4<CostLines!$N11+CostLines!$O11)),CostLines!$P11,0)) -> 3333.3333 | ... AO35: =IF(CostLines!$F11="One-time",IF(AO$4=CostLines!$N11,CostLines!$J11,0),IF(AND(AO$4>=CostLines!$N11,IF(CostLines!$O11="",TRUE(),AO$4<CostLines!$N11+CostLines!$O11)),CostLines!$P11,0)) -> 3333.3333
A36: =CostLines!B12 -> AM feedstock & lab consumables | B36: =CostLines!C12 -> EnergyWave, Inc. | C36: =CostLines!D12 -> Operations | D36: =CostLines!E12 -> Consumables | E36: =SUM(F36:AO36) -> 340000 | F36: =IF(CostLines!$F12="One-time",IF(F$4=CostLines!$N12,CostLines!$J12,0),IF(AND(F$4>=CostLines!$N12,IF(CostLines!$O12="",TRUE(),F$4<CostLines!$N12+CostLines!$O12)),CostLines!$P12,0)) -> 0 | G36: =IF(CostLines!$F12="One-time",IF(G$4=CostLines!$N12,CostLines!$J12,0),IF(AND(G$4>=CostLines!$N12,IF(CostLines!$O12="",TRUE(),G$4<CostLines!$N12+CostLines!$O12)),CostLines!$P12,0)) -> 0 | H36: =IF(CostLines!$F12="One-time",IF(H$4=CostLines!$N12,CostLines!$J12,0),IF(AND(H$4>=CostLines!$N12,IF(CostLines!$O12="",TRUE(),H$4<CostLines!$N12+CostLines!$O12)),CostLines!$P12,0)) -> 10000 | I36: =IF(CostLines!$F12="One-time",IF(I$4=CostLines!$N12,CostLines!$J12,0),IF(AND(I$4>=CostLines!$N12,IF(CostLines!$O12="",TRUE(),I$4<CostLines!$N12+CostLines!$O12)),CostLines!$P12,0)) -> 10000 | J36: =IF(CostLines!$F12="One-time",IF(J$4=CostLines!$N12,CostLines!$J12,0),IF(AND(J$4>=CostLines!$N12,IF(CostLines!$O12="",TRUE(),J$4<CostLines!$N12+CostLines!$O12)),CostLines!$P12,0)) -> 10000 | K36: =IF(CostLines!$F12="One-time",IF(K$4=CostLines!$N12,CostLines!$J12,0),IF(AND(K$4>=CostLines!$N12,IF(CostLines!$O12="",TRUE(),K$4<CostLines!$N12+CostLines!$O12)),CostLines!$P12,0)) -> 10000 | L36: =IF(CostLines!$F12="One-time",IF(L$4=CostLines!$N12,CostLines!$J12,0),IF(AND(L$4>=CostLines!$N12,IF(CostLines!$O12="",TRUE(),L$4<CostLines!$N12+CostLines!$O12)),CostLines!$P12,0)) -> 10000 | M36: =IF(CostLines!$F12="One-time",IF(M$4=CostLines!$N12,CostLines!$J12,0),IF(AND(M$4>=CostLines!$N12,IF(CostLines!$O12="",TRUE(),M$4<CostLines!$N12+CostLines!$O12)),CostLines!$P12,0)) -> 10000 | ... AO36: =IF(CostLines!$F12="One-time",IF(AO$4=CostLines!$N12,CostLines!$J12,0),IF(AND(AO$4>=CostLines!$N12,IF(CostLines!$O12="",TRUE(),AO$4<CostLines!$N12+CostLines!$O12)),CostLines!$P12,0)) -> 10000
A37: =CostLines!B13 -> Compute, simulation & software licenses | B37: =CostLines!C13 -> EnergyWave, Inc. | C37: =CostLines!D13 -> Operations | D37: =CostLines!E13 -> Compute | E37: =SUM(F37:AO37) -> 288000 | F37: =IF(CostLines!$F13="One-time",IF(F$4=CostLines!$N13,CostLines!$J13,0),IF(AND(F$4>=CostLines!$N13,IF(CostLines!$O13="",TRUE(),F$4<CostLines!$N13+CostLines!$O13)),CostLines!$P13,0)) -> 8000 | G37: =IF(CostLines!$F13="One-time",IF(G$4=CostLines!$N13,CostLines!$J13,0),IF(AND(G$4>=CostLines!$N13,IF(CostLines!$O13="",TRUE(),G$4<CostLines!$N13+CostLines!$O13)),CostLines!$P13,0)) -> 8000 | H37: =IF(CostLines!$F13="One-time",IF(H$4=CostLines!$N13,CostLines!$J13,0),IF(AND(H$4>=CostLines!$N13,IF(CostLines!$O13="",TRUE(),H$4<CostLines!$N13+CostLines!$O13)),CostLines!$P13,0)) -> 8000 | I37: =IF(CostLines!$F13="One-time",IF(I$4=CostLines!$N13,CostLines!$J13,0),IF(AND(I$4>=CostLines!$N13,IF(CostLines!$O13="",TRUE(),I$4<CostLines!$N13+CostLines!$O13)),CostLines!$P13,0)) -> 8000 | J37: =IF(CostLines!$F13="One-time",IF(J$4=CostLines!$N13,CostLines!$J13,0),IF(AND(J$4>=CostLines!$N13,IF(CostLines!$O13="",TRUE(),J$4<CostLines!$N13+CostLines!$O13)),CostLines!$P13,0)) -> 8000 | K37: =IF(CostLines!$F13="One-time",IF(K$4=CostLines!$N13,CostLines!$J13,0),IF(AND(K$4>=CostLines!$N13,IF(CostLines!$O13="",TRUE(),K$4<CostLines!$N13+CostLines!$O13)),CostLines!$P13,0)) -> 8000 | L37: =IF(CostLines!$F13="One-time",IF(L$4=CostLines!$N13,CostLines!$J13,0),IF(AND(L$4>=CostLines!$N13,IF(CostLines!$O13="",TRUE(),L$4<CostLines!$N13+CostLines!$O13)),CostLines!$P13,0)) -> 8000 | M37: =IF(CostLines!$F13="One-time",IF(M$4=CostLines!$N13,CostLines!$J13,0),IF(AND(M$4>=CostLines!$N13,IF(CostLines!$O13="",TRUE(),M$4<CostLines!$N13+CostLines!$O13)),CostLines!$P13,0)) -> 8000 | ... AO37: =IF(CostLines!$F13="One-time",IF(AO$4=CostLines!$N13,CostLines!$J13,0),IF(AND(AO$4>=CostLines!$N13,IF(CostLines!$O13="",TRUE(),AO$4<CostLines!$N13+CostLines!$O13)),CostLines!$P13,0)) -> 8000
A38: =CostLines!B14 -> Independent third-party replication / verification | B38: =CostLines!C14 -> EnergyWave, Inc. | C38: =CostLines!D14 -> Research | D38: =CostLines!E14 -> External verification | E38: =SUM(F38:AO38) -> 375000 | F38: =IF(CostLines!$F14="One-time",IF(F$4=CostLines!$N14,CostLines!$J14,0),IF(AND(F$4>=CostLines!$N14,IF(CostLines!$O14="",TRUE(),F$4<CostLines!$N14+CostLines!$O14)),CostLines!$P14,0)) -> 0 | G38: =IF(CostLines!$F14="One-time",IF(G$4=CostLines!$N14,CostLines!$J14,0),IF(AND(G$4>=CostLines!$N14,IF(CostLines!$O14="",TRUE(),G$4<CostLines!$N14+CostLines!$O14)),CostLines!$P14,0)) -> 0 | H38: =IF(CostLines!$F14="One-time",IF(H$4=CostLines!$N14,CostLines!$J14,0),IF(AND(H$4>=CostLines!$N14,IF(CostLines!$O14="",TRUE(),H$4<CostLines!$N14+CostLines!$O14)),CostLines!$P14,0)) -> 0 | I38: =IF(CostLines!$F14="One-time",IF(I$4=CostLines!$N14,CostLines!$J14,0),IF(AND(I$4>=CostLines!$N14,IF(CostLines!$O14="",TRUE(),I$4<CostLines!$N14+CostLines!$O14)),CostLines!$P14,0)) -> 0 | J38: =IF(CostLines!$F14="One-time",IF(J$4=CostLines!$N14,CostLines!$J14,0),IF(AND(J$4>=CostLines!$N14,IF(CostLines!$O14="",TRUE(),J$4<CostLines!$N14+CostLines!$O14)),CostLines!$P14,0)) -> 0 | K38: =IF(CostLines!$F14="One-time",IF(K$4=CostLines!$N14,CostLines!$J14,0),IF(AND(K$4>=CostLines!$N14,IF(CostLines!$O14="",TRUE(),K$4<CostLines!$N14+CostLines!$O14)),CostLines!$P14,0)) -> 0 | L38: =IF(CostLines!$F14="One-time",IF(L$4=CostLines!$N14,CostLines!$J14,0),IF(AND(L$4>=CostLines!$N14,IF(CostLines!$O14="",TRUE(),L$4<CostLines!$N14+CostLines!$O14)),CostLines!$P14,0)) -> 12500 | M38: =IF(CostLines!$F14="One-time",IF(M$4=CostLines!$N14,CostLines!$J14,0),IF(AND(M$4>=CostLines!$N14,IF(CostLines!$O14="",TRUE(),M$4<CostLines!$N14+CostLines!$O14)),CostLines!$P14,0)) -> 12500 | ... AO38: =IF(CostLines!$F14="One-time",IF(AO$4=CostLines!$N14,CostLines!$J14,0),IF(AND(AO$4>=CostLines!$N14,IF(CostLines!$O14="",TRUE(),AO$4<CostLines!$N14+CostLines!$O14)),CostLines!$P14,0)) -> 12500
A39: =CostLines!B15 -> UCI / NFCRC facility-use or sponsored-research agreement | B39: =CostLines!C15 -> EnergyWave, Inc. | C39: =CostLines!D15 -> Research | D39: =CostLines!E15 -> University partnership | E39: =SUM(F39:AO39) -> 425000 | F39: =IF(CostLines!$F15="One-time",IF(F$4=CostLines!$N15,CostLines!$J15,0),IF(AND(F$4>=CostLines!$N15,IF(CostLines!$O15="",TRUE(),F$4<CostLines!$N15+CostLines!$O15)),CostLines!$P15,0)) -> 0 | G39: =IF(CostLines!$F15="One-time",IF(G$4=CostLines!$N15,CostLines!$J15,0),IF(AND(G$4>=CostLines!$N15,IF(CostLines!$O15="",TRUE(),G$4<CostLines!$N15+CostLines!$O15)),CostLines!$P15,0)) -> 0 | H39: =IF(CostLines!$F15="One-time",IF(H$4=CostLines!$N15,CostLines!$J15,0),IF(AND(H$4>=CostLines!$N15,IF(CostLines!$O15="",TRUE(),H$4<CostLines!$N15+CostLines!$O15)),CostLines!$P15,0)) -> 12500 | I39: =IF(CostLines!$F15="One-time",IF(I$4=CostLines!$N15,CostLines!$J15,0),IF(AND(I$4>=CostLines!$N15,IF(CostLines!$O15="",TRUE(),I$4<CostLines!$N15+CostLines!$O15)),CostLines!$P15,0)) -> 12500 | J39: =IF(CostLines!$F15="One-time",IF(J$4=CostLines!$N15,CostLines!$J15,0),IF(AND(J$4>=CostLines!$N15,IF(CostLines!$O15="",TRUE(),J$4<CostLines!$N15+CostLines!$O15)),CostLines!$P15,0)) -> 12500 | K39: =IF(CostLines!$F15="One-time",IF(K$4=CostLines!$N15,CostLines!$J15,0),IF(AND(K$4>=CostLines!$N15,IF(CostLines!$O15="",TRUE(),K$4<CostLines!$N15+CostLines!$O15)),CostLines!$P15,0)) -> 12500 | L39: =IF(CostLines!$F15="One-time",IF(L$4=CostLines!$N15,CostLines!$J15,0),IF(AND(L$4>=CostLines!$N15,IF(CostLines!$O15="",TRUE(),L$4<CostLines!$N15+CostLines!$O15)),CostLines!$P15,0)) -> 12500 | M39: =IF(CostLines!$F15="One-time",IF(M$4=CostLines!$N15,CostLines!$J15,0),IF(AND(M$4>=CostLines!$N15,IF(CostLines!$O15="",TRUE(),M$4<CostLines!$N15+CostLines!$O15)),CostLines!$P15,0)) -> 12500 | ... AO39: =IF(CostLines!$F15="One-time",IF(AO$4=CostLines!$N15,CostLines!$J15,0),IF(AND(AO$4>=CostLines!$N15,IF(CostLines!$O15="",TRUE(),AO$4<CostLines!$N15+CostLines!$O15)),CostLines!$P15,0)) -> 12500
... A54: =CostLines!B30 -> Intercompany services to/from GovThink Institute & pinnacle.blog (arms-length) | B54: =CostLines!C30 -> EnergyWave, Inc. | C54: =CostLines!D30 -> Intercompany | D54: =CostLines!E30 -> Affiliates | E54: =SUM(F54:AO54) -> 0 | F54: =IF(CostLines!$F30="One-time",IF(F$4=CostLines!$N30,CostLines!$J30,0),IF(AND(F$4>=CostLines!$N30,IF(CostLines!$O30="",TRUE(),F$4<CostLines!$N30+CostLines!$O30)),CostLines!$P30,0)) -> 0 | G54: =IF(CostLines!$F30="One-time",IF(G$4=CostLines!$N30,CostLines!$J30,0),IF(AND(G$4>=CostLines!$N30,IF(CostLines!$O30="",TRUE(),G$4<CostLines!$N30+CostLines!$O30)),CostLines!$P30,0)) -> 0 | H54: =IF(CostLines!$F30="One-time",IF(H$4=CostLines!$N30,CostLines!$J30,0),IF(AND(H$4>=CostLines!$N30,IF(CostLines!$O30="",TRUE(),H$4<CostLines!$N30+CostLines!$O30)),CostLines!$P30,0)) -> 0 | I54: =IF(CostLines!$F30="One-time",IF(I$4=CostLines!$N30,CostLines!$J30,0),IF(AND(I$4>=CostLines!$N30,IF(CostLines!$O30="",TRUE(),I$4<CostLines!$N30+CostLines!$O30)),CostLines!$P30,0)) -> 0 | J54: =IF(CostLines!$F30="One-time",IF(J$4=CostLines!$N30,CostLines!$J30,0),IF(AND(J$4>=CostLines!$N30,IF(CostLines!$O30="",TRUE(),J$4<CostLines!$N30+CostLines!$O30)),CostLines!$P30,0)) -> 0 | K54: =IF(CostLines!$F30="One-time",IF(K$4=CostLines!$N30,CostLines!$J30,0),IF(AND(K$4>=CostLines!$N30,IF(CostLines!$O30="",TRUE(),K$4<CostLines!$N30+CostLines!$O30)),CostLines!$P30,0)) -> 0 | L54: =IF(CostLines!$F30="One-time",IF(L$4=CostLines!$N30,CostLines!$J30,0),IF(AND(L$4>=CostLines!$N30,IF(CostLines!$O30="",TRUE(),L$4<CostLines!$N30+CostLines!$O30)),CostLines!$P30,0)) -> 0 | M54: =IF(CostLines!$F30="One-time",IF(M$4=CostLines!$N30,CostLines!$J30,0),IF(AND(M$4>=CostLines!$N30,IF(CostLines!$O30="",TRUE(),M$4<CostLines!$N30+CostLines!$O30)),CostLines!$P30,0)) -> 0 | ... AO54: =IF(CostLines!$F30="One-time",IF(AO$4=CostLines!$N30,CostLines!$J30,0),IF(AND(AO$4>=CostLines!$N30,IF(CostLines!$O30="",TRUE(),AO$4<CostLines!$N30+CostLines!$O30)),CostLines!$P30,0)) -> 0
A56: TOTALS BY CATEGORY
A57: Payroll | E57: =SUM(F57:AO57) -> 6905508.3 | F57: =SUMIF($C$8:$C$54,$A57,F$8:F$54) -> 55241.667 | G57: =SUMIF($C$8:$C$54,$A57,G$8:G$54) -> 161583.33 | H57: =SUMIF($C$8:$C$54,$A57,H$8:H$54) -> 197333.33 | I57: =SUMIF($C$8:$C$54,$A57,I$8:I$54) -> 219950 | J57: =SUMIF($C$8:$C$54,$A57,J$8:J$54) -> 220200 | K57: =SUMIF($C$8:$C$54,$A57,K$8:K$54) -> 195200 | L57: =SUMIF($C$8:$C$54,$A57,L$8:L$54) -> 195200 | M57: =SUMIF($C$8:$C$54,$A57,M$8:M$54) -> 195200 | ... AO57: =SUMIF($C$8:$C$54,$A57,AO$8:AO$54) -> 195200
A58: Consulting | E58: =SUM(F58:AO58) -> 3546666.7 | F58: =SUMIF($C$8:$C$54,$A58,F$8:F$54) -> 59166.667 | G58: =SUMIF($C$8:$C$54,$A58,G$8:G$54) -> 59166.667 | H58: =SUMIF($C$8:$C$54,$A58,H$8:H$54) -> 100833.33 | I58: =SUMIF($C$8:$C$54,$A58,I$8:I$54) -> 100833.33 | J58: =SUMIF($C$8:$C$54,$A58,J$8:J$54) -> 100833.33 | K58: =SUMIF($C$8:$C$54,$A58,K$8:K$54) -> 100833.33 | L58: =SUMIF($C$8:$C$54,$A58,L$8:L$54) -> 100833.33 | M58: =SUMIF($C$8:$C$54,$A58,M$8:M$54) -> 100833.33 | ... AO58: =SUMIF($C$8:$C$54,$A58,AO$8:AO$54) -> 100833.33
A59: Facilities | E59: =SUM(F59:AO59) -> 1272500 | F59: =SUMIF($C$8:$C$54,$A59,F$8:F$54) -> 0 | G59: =SUMIF($C$8:$C$54,$A59,G$8:G$54) -> 371500 | H59: =SUMIF($C$8:$C$54,$A59,H$8:H$54) -> 26500 | I59: =SUMIF($C$8:$C$54,$A59,I$8:I$54) -> 26500 | J59: =SUMIF($C$8:$C$54,$A59,J$8:J$54) -> 26500 | K59: =SUMIF($C$8:$C$54,$A59,K$8:K$54) -> 26500 | L59: =SUMIF($C$8:$C$54,$A59,L$8:L$54) -> 26500 | M59: =SUMIF($C$8:$C$54,$A59,M$8:M$54) -> 26500 | ... AO59: =SUMIF($C$8:$C$54,$A59,AO$8:AO$54) -> 26500
A60: Equipment | E60: =SUM(F60:AO60) -> 1395000 | F60: =SUMIF($C$8:$C$54,$A60,F$8:F$54) -> 0 | G60: =SUMIF($C$8:$C$54,$A60,G$8:G$54) -> 450000 | H60: =SUMIF($C$8:$C$54,$A60,H$8:H$54) -> 752500 | I60: =SUMIF($C$8:$C$54,$A60,I$8:I$54) -> 5833.3333 | J60: =SUMIF($C$8:$C$54,$A60,J$8:J$54) -> 5833.3333 | K60: =SUMIF($C$8:$C$54,$A60,K$8:K$54) -> 5833.3333 | L60: =SUMIF($C$8:$C$54,$A60,L$8:L$54) -> 5833.3333 | M60: =SUMIF($C$8:$C$54,$A60,M$8:M$54) -> 5833.3333 | ... AO60: =SUMIF($C$8:$C$54,$A60,AO$8:AO$54) -> 5833.3333
A61: Operations | E61: =SUM(F61:AO61) -> 628000 | F61: =SUMIF($C$8:$C$54,$A61,F$8:F$54) -> 8000 | G61: =SUMIF($C$8:$C$54,$A61,G$8:G$54) -> 8000 | H61: =SUMIF($C$8:$C$54,$A61,H$8:H$54) -> 18000 | I61: =SUMIF($C$8:$C$54,$A61,I$8:I$54) -> 18000 | J61: =SUMIF($C$8:$C$54,$A61,J$8:J$54) -> 18000 | K61: =SUMIF($C$8:$C$54,$A61,K$8:K$54) -> 18000 | L61: =SUMIF($C$8:$C$54,$A61,L$8:L$54) -> 18000 | M61: =SUMIF($C$8:$C$54,$A61,M$8:M$54) -> 18000 | ... AO61: =SUMIF($C$8:$C$54,$A61,AO$8:AO$54) -> 18000
A62: Research | E62: =SUM(F62:AO62) -> 905000 | F62: =SUMIF($C$8:$C$54,$A62,F$8:F$54) -> 0 | G62: =SUMIF($C$8:$C$54,$A62,G$8:G$54) -> 3000 | H62: =SUMIF($C$8:$C$54,$A62,H$8:H$54) -> 15500 | I62: =SUMIF($C$8:$C$54,$A62,I$8:I$54) -> 15500 | J62: =SUMIF($C$8:$C$54,$A62,J$8:J$54) -> 15500 | K62: =SUMIF($C$8:$C$54,$A62,K$8:K$54) -> 15500 | L62: =SUMIF($C$8:$C$54,$A62,L$8:L$54) -> 28000 | M62: =SUMIF($C$8:$C$54,$A62,M$8:M$54) -> 28000 | ... AO62: =SUMIF($C$8:$C$54,$A62,AO$8:AO$54) -> 28000
A63: Legal | E63: =SUM(F63:AO63) -> 855000 | F63: =SUMIF($C$8:$C$54,$A63,F$8:F$54) -> 155000 | G63: =SUMIF($C$8:$C$54,$A63,G$8:G$54) -> 20000 | H63: =SUMIF($C$8:$C$54,$A63,H$8:H$54) -> 20000 | I63: =SUMIF($C$8:$C$54,$A63,I$8:I$54) -> 20000 | J63: =SUMIF($C$8:$C$54,$A63,J$8:J$54) -> 20000 | K63: =SUMIF($C$8:$C$54,$A63,K$8:K$54) -> 20000 | L63: =SUMIF($C$8:$C$54,$A63,L$8:L$54) -> 20000 | M63: =SUMIF($C$8:$C$54,$A63,M$8:M$54) -> 20000 | ... AO63: =SUMIF($C$8:$C$54,$A63,AO$8:AO$54) -> 20000
A64: Finance | E64: =SUM(F64:AO64) -> 737333.33 | F64: =SUMIF($C$8:$C$54,$A64,F$8:F$54) -> 26500 | G64: =SUMIF($C$8:$C$54,$A64,G$8:G$54) -> 26500 | H64: =SUMIF($C$8:$C$54,$A64,H$8:H$54) -> 26500 | I64: =SUMIF($C$8:$C$54,$A64,I$8:I$54) -> 26500 | J64: =SUMIF($C$8:$C$54,$A64,J$8:J$54) -> 26500 | K64: =SUMIF($C$8:$C$54,$A64,K$8:K$54) -> 26500 | L64: =SUMIF($C$8:$C$54,$A64,L$8:L$54) -> 16500 | M64: =SUMIF($C$8:$C$54,$A64,M$8:M$54) -> 16500 | ... AO64: =SUMIF($C$8:$C$54,$A64,AO$8:AO$54) -> 19833.333
A65: G&A | E65: =SUM(F65:AO65) -> 828000 | F65: =SUMIF($C$8:$C$54,$A65,F$8:F$54) -> 215500 | G65: =SUMIF($C$8:$C$54,$A65,G$8:G$54) -> 85500 | H65: =SUMIF($C$8:$C$54,$A65,H$8:H$54) -> 15500 | I65: =SUMIF($C$8:$C$54,$A65,I$8:I$54) -> 15500 | J65: =SUMIF($C$8:$C$54,$A65,J$8:J$54) -> 15500 | K65: =SUMIF($C$8:$C$54,$A65,K$8:K$54) -> 15500 | L65: =SUMIF($C$8:$C$54,$A65,L$8:L$54) -> 15500 | M65: =SUMIF($C$8:$C$54,$A65,M$8:M$54) -> 15500 | ... AO65: =SUMIF($C$8:$C$54,$A65,AO$8:AO$54) -> 15500
A66: Intercompany | E66: =SUM(F66:AO66) -> 0 | F66: =SUMIF($C$8:$C$54,$A66,F$8:F$54) -> 0 | G66: =SUMIF($C$8:$C$54,$A66,G$8:G$54) -> 0 | H66: =SUMIF($C$8:$C$54,$A66,H$8:H$54) -> 0 | I66: =SUMIF($C$8:$C$54,$A66,I$8:I$54) -> 0 | J66: =SUMIF($C$8:$C$54,$A66,J$8:J$54) -> 0 | K66: =SUMIF($C$8:$C$54,$A66,K$8:K$54) -> 0 | L66: =SUMIF($C$8:$C$54,$A66,L$8:L$54) -> 0 | M66: =SUMIF($C$8:$C$54,$A66,M$8:M$54) -> 0 | ... AO66: =SUMIF($C$8:$C$54,$A66,AO$8:AO$54) -> 0
A67: Total plan spend | E67: =SUM(F67:AO67) -> 17073008 | F67: =SUM(F57:F66) -> 519408.33 | G67: =SUM(G57:G66) -> 1185250 | H67: =SUM(H57:H66) -> 1172666.7 | I67: =SUM(I57:I66) -> 448616.67 | J67: =SUM(J57:J66) -> 448866.67 | K67: =SUM(K57:K66) -> 423866.67 | L67: =SUM(L57:L66) -> 426366.67 | M67: =SUM(M57:M66) -> 426366.67 | ... AO67: =SUM(AO57:AO66) -> 429700
A68: Cumulative plan spend | F68: =SUM($F$67:F67) -> 519408.33 | G68: =SUM($F$67:G67) -> 1704658.3 | H68: =SUM($F$67:H67) -> 2877325 | I68: =SUM($F$67:I67) -> 3325941.7 | J68: =SUM($F$67:J67) -> 3774808.3 | K68: =SUM($F$67:K67) -> 4198675 | L68: =SUM($F$67:L67) -> 4625041.7 | M68: =SUM($F$67:M67) -> 5051408.3 | ... AO68: =SUM($F$67:AO67) -> 17073008
A69: Reserve accrual (ReservePct × spend) | E69: =SUM(F69:AO69) -> 3414601.7 | F69: =F67*ReservePct -> 103881.67 | G69: =G67*ReservePct -> 237050 | H69: =H67*ReservePct -> 234533.33 | I69: =I67*ReservePct -> 89723.333 | J69: =J67*ReservePct -> 89773.333 | K69: =K67*ReservePct -> 84773.333 | L69: =L67*ReservePct -> 85273.333 | M69: =M67*ReservePct -> 85273.333 | ... AO69: =AO67*ReservePct -> 85940
A70: Cumulative need incl. reserve | F70: =F68+SUM($F$69:F69) -> 623290 | G70: =G68+SUM($F$69:G69) -> 2045590 | H70: =H68+SUM($F$69:H69) -> 3452790 | I70: =I68+SUM($F$69:I69) -> 3991130 | J70: =J68+SUM($F$69:J69) -> 4529770 | K70: =K68+SUM($F$69:K69) -> 5038410 | L70: =L68+SUM($F$69:L69) -> 5550050 | M70: =M68+SUM($F$69:M69) -> 6061690 | ... AO70: =AO68+SUM($F$69:AO69) -> 20487610
A71: Cash remaining (single close at month 1, raise = UseOfFunds!C6) | F71: =RaiseSize-F68 -> 19968202 | G71: =RaiseSize-G68 -> 18782952 | H71: =RaiseSize-H68 -> 17610285 | I71: =RaiseSize-I68 -> 17161668 | J71: =RaiseSize-J68 -> 16712802 | K71: =RaiseSize-K68 -> 16288935 | L71: =RaiseSize-L68 -> 15862568 | M71: =RaiseSize-M68 -> 15436202 | ... AO71: =RaiseSize-AO68 -> 3414601.7
A72: Check: detail rows − category totals (must be 0) | E72: =SUM(E8:E54)-E67 -> 0

Sheet UseOfFunds
A1: Use of funds & raise sizing — packet page
A2: Scenario: | B2: =ScenarioName -> Base
B4: Plan spend, 36 months ($) | C4: =Monthly!E67 -> 17073008
B5: Reserve / contingency ($) | C5: =C4*ReservePct -> 3414601.7 | D5: =ReservePct -> 0.2
B6: RAISE SIZE — plan + reserve ($) | C6: =C4+C5 -> 20487610
B8: Category | C8: Year 1 ($) | D8: Year 2 ($) | E8: Year 3 ($) | F8: Total ($) | G8: % of plan
B9: Payroll | C9: =SUM(Monthly!F57:Q57) -> 2220708.3 | D9: =SUM(Monthly!R57:AC57) -> 2342400 | E9: =SUM(Monthly!AD57:AO57) -> 2342400 | F9: =SUM(C9:E9) -> 6905508.3 | G9: =IF($F$19=0,0,F9/$F$19) -> 0.40446934
B10: Consulting | C10: =SUM(Monthly!F58:Q58) -> 1126666.7 | D10: =SUM(Monthly!R58:AC58) -> 1210000 | E10: =SUM(Monthly!AD58:AO58) -> 1210000 | F10: =SUM(C10:E10) -> 3546666.7 | G10: =IF($F$19=0,0,F10/$F$19) -> 0.20773531
B11: Facilities | C11: =SUM(Monthly!F59:Q59) -> 636500 | D11: =SUM(Monthly!R59:AC59) -> 318000 | E11: =SUM(Monthly!AD59:AO59) -> 318000 | F11: =SUM(C11:E11) -> 1272500 | G11: =IF($F$19=0,0,F11/$F$19) -> 0.074532852
B12: Equipment | C12: =SUM(Monthly!F60:Q60) -> 1255000 | D12: =SUM(Monthly!R60:AC60) -> 70000 | E12: =SUM(Monthly!AD60:AO60) -> 70000 | F12: =SUM(C12:E12) -> 1395000 | G12: =IF($F$19=0,0,F12/$F$19) -> 0.08170792
B13: Operations | C13: =SUM(Monthly!F61:Q61) -> 196000 | D13: =SUM(Monthly!R61:AC61) -> 216000 | E13: =SUM(Monthly!AD61:AO61) -> 216000 | F13: =SUM(C13:E13) -> 628000 | G13: =IF($F$19=0,0,F13/$F$19) -> 0.036783207
B14: Research | C14: =SUM(Monthly!F62:Q62) -> 233000 | D14: =SUM(Monthly!R62:AC62) -> 336000 | E14: =SUM(Monthly!AD62:AO62) -> 336000 | F14: =SUM(C14:E14) -> 905000 | G14: =IF($F$19=0,0,F14/$F$19) -> 0.053007647
B15: Legal | C15: =SUM(Monthly!F63:Q63) -> 375000 | D15: =SUM(Monthly!R63:AC63) -> 240000 | E15: =SUM(Monthly!AD63:AO63) -> 240000 | F15: =SUM(C15:E15) -> 855000 | G15: =IF($F$19=0,0,F15/$F$19) -> 0.050079048
B16: Finance | C16: =SUM(Monthly!F64:Q64) -> 261333.33 | D16: =SUM(Monthly!R64:AC64) -> 238000 | E16: =SUM(Monthly!AD64:AO64) -> 238000 | F16: =SUM(C16:E16) -> 737333.33 | G16: =IF($F$19=0,0,F16/$F$19) -> 0.043187077
B17: G&A | C17: =SUM(Monthly!F65:Q65) -> 456000 | D17: =SUM(Monthly!R65:AC65) -> 186000 | E17: =SUM(Monthly!AD65:AO65) -> 186000 | F17: =SUM(C17:E17) -> 828000 | G17: =IF($F$19=0,0,F17/$F$19) -> 0.048497604
B18: Intercompany | C18: =SUM(Monthly!F66:Q66) -> 0 | D18: =SUM(Monthly!R66:AC66) -> 0 | E18: =SUM(Monthly!AD66:AO66) -> 0 | F18: =SUM(C18:E18) -> 0 | G18: =IF($F$19=0,0,F18/$F$19) -> 0
B19: Total plan spend | C19: =SUM(C9:C18) -> 6760208.3 | D19: =SUM(D9:D18) -> 5156400 | E19: =SUM(E9:E18) -> 5156400 | F19: =SUM(F9:F18) -> 17073008 | G19: =IF(F19=0,0,SUM(G9:G18)) -> 1
B20: Reserve / contingency | F20: =C5 -> 3414601.7
B21: Raise size | F21: =C6 -> 20487610
B23: Gate tranche | C23: Month | D23: Cumulative need incl. reserve ($) | E23: Tranche increment ($) | F23: Cumulative people on plan
B24: Gate 1 — Characterize | C24: =Gate1 -> 9 | D24: =INDEX(Monthly!$F$70:$AO$70,1,C24) -> 6573330 | E24: =D24 -> 6573330 | F24: =COUNTIF(Headcount!$M$4:$M$21,"<="&C24) -> 18
B25: Gate 2 — Conservation test | C25: =Gate2 -> 21 | D25: =INDEX(Monthly!$F$70:$AO$70,1,C25) -> 12753010 | E25: =D25-D24 -> 6179680 | F25: =COUNTIF(Headcount!$M$4:$M$21,"<="&C25) -> 18
B26: Gate 3 — Extract or retire (published) | C26: =Gate3 -> 36 | D26: =INDEX(Monthly!$F$70:$AO$70,1,C26) -> 20487610 | E26: =D26-D25 -> 7734600 | F26: =COUNTIF(Headcount!$M$4:$M$21,"<="&C26) -> 18
B27: Tranche reading: cumulative need at each gate month is the cash the company must have had by then. A gate-tranched close (or milestone-released escrow) maps to these three numbers.
B29: Spend shape | C29: Amount ($) | D29: % of plan
B30: One-time (equipment, build-out, deposits, formation, recruiting, relocation) | C30: =SUMIF(CostLines!$F$4:$F$30,"One-time",CostLines!$Q$4:$Q$30)+Monthly!E26 -> 2145000 | D30: =IF($C$4=0,0,C30/$C$4) -> 0.12563691
B31: Recurring (payroll, consulting, lease, operations, retainers) | C31: =C4-C30 -> 14928008 | D31: =IF($C$4=0,0,C31/$C$4) -> 0.87436309
B33: People on plan (cumulative) | C33: Month 6 | D33: Month 12 | E33: Month 24 | F33: Month 36
B34: All roles (W-2 + consulting agreements) | C34: =COUNTIF(Headcount!$M$4:$M$21,"<="&6) -> 18 | D34: =COUNTIF(Headcount!$M$4:$M$21,"<="&12) -> 18 | E34: =COUNTIF(Headcount!$M$4:$M$21,"<="&24) -> 18 | F34: =COUNTIF(Headcount!$M$4:$M$21,"<="&36) -> 18
B35: Average monthly burn in that month ($) | C35: =Monthly!K67 -> 423866.67 | D35: =Monthly!Q67 -> 429700 | E35: =Monthly!AC67 -> 429700 | F35: =Monthly!AO67 -> 429700
B37: Model checks (must be 0) | C37: Value
B38: Pivot_Data total − plan spend | C38: =SUM(Pivot_Data!G:G)-C4 -> 0
B39: Monthly detail − category totals | C39: =Monthly!E72 -> 0
B40: CostLines total + Headcount total − plan spend | C40: =CostLines!Q31+Headcount!O22-C4 -> 0

Sheet Pivot_Data
A1: Month # | B1: Month | C1: Entity | D1: Category | E1: Subcategory | F1: Line | G1: Amount ($) | H1: Scenario
A2: 1 | B2: =EDATE(StartDate,A2-1) -> 46388 | C2: =Monthly!$B$8 -> EnergyWave, Inc. | D2: =Monthly!$C$8 -> Payroll | E2: =Monthly!$D$8 -> Salary & load | F2: =Monthly!$A$8 -> Founder & CEO | G2: =Monthly!F$8 -> 24400 | H2: =ScenarioName -> Base
A3: 2 | B3: =EDATE(StartDate,A3-1) -> 46419 | C3: =Monthly!$B$8 -> EnergyWave, Inc. | D3: =Monthly!$C$8 -> Payroll | E3: =Monthly!$D$8 -> Salary & load | F3: =Monthly!$A$8 -> Founder & CEO | G3: =Monthly!G$8 -> 24400 | H3: =ScenarioName -> Base
A4: 3 | B4: =EDATE(StartDate,A4-1) -> 46447 | C4: =Monthly!$B$8 -> EnergyWave, Inc. | D4: =Monthly!$C$8 -> Payroll | E4: =Monthly!$D$8 -> Salary & load | F4: =Monthly!$A$8 -> Founder & CEO | G4: =Monthly!H$8 -> 24400 | H4: =ScenarioName -> Base
A5: 4 | B5: =EDATE(StartDate,A5-1) -> 46478 | C5: =Monthly!$B$8 -> EnergyWave, Inc. | D5: =Monthly!$C$8 -> Payroll | E5: =Monthly!$D$8 -> Salary & load | F5: =Monthly!$A$8 -> Founder & CEO | G5: =Monthly!I$8 -> 24400 | H5: =ScenarioName -> Base
A6: 5 | B6: =EDATE(StartDate,A6-1) -> 46508 | C6: =Monthly!$B$8 -> EnergyWave, Inc. | D6: =Monthly!$C$8 -> Payroll | E6: =Monthly!$D$8 -> Salary & load | F6: =Monthly!$A$8 -> Founder & CEO | G6: =Monthly!J$8 -> 24400 | H6: =ScenarioName -> Base
A7: 6 | B7: =EDATE(StartDate,A7-1) -> 46539 | C7: =Monthly!$B$8 -> EnergyWave, Inc. | D7: =Monthly!$C$8 -> Payroll | E7: =Monthly!$D$8 -> Salary & load | F7: =Monthly!$A$8 -> Founder & CEO | G7: =Monthly!K$8 -> 24400 | H7: =ScenarioName -> Base
A8: 7 | B8: =EDATE(StartDate,A8-1) -> 46569 | C8: =Monthly!$B$8 -> EnergyWave, Inc. | D8: =Monthly!$C$8 -> Payroll | E8: =Monthly!$D$8 -> Salary & load | F8: =Monthly!$A$8 -> Founder & CEO | G8: =Monthly!L$8 -> 24400 | H8: =ScenarioName -> Base
A9: 8 | B9: =EDATE(StartDate,A9-1) -> 46600 | C9: =Monthly!$B$8 -> EnergyWave, Inc. | D9: =Monthly!$C$8 -> Payroll | E9: =Monthly!$D$8 -> Salary & load | F9: =Monthly!$A$8 -> Founder & CEO | G9: =Monthly!M$8 -> 24400 | H9: =ScenarioName -> Base
A10: 9 | B10: =EDATE(StartDate,A10-1) -> 46631 | C10: =Monthly!$B$8 -> EnergyWave, Inc. | D10: =Monthly!$C$8 -> Payroll | E10: =Monthly!$D$8 -> Salary & load | F10: =Monthly!$A$8 -> Founder & CEO | G10: =Monthly!N$8 -> 24400 | H10: =ScenarioName -> Base
A11: 10 | B11: =EDATE(StartDate,A11-1) -> 46661 | C11: =Monthly!$B$8 -> EnergyWave, Inc. | D11: =Monthly!$C$8 -> Payroll | E11: =Monthly!$D$8 -> Salary & load | F11: =Monthly!$A$8 -> Founder & CEO | G11: =Monthly!O$8 -> 24400 | H11: =ScenarioName -> Base
A12: 11 | B12: =EDATE(StartDate,A12-1) -> 46692 | C12: =Monthly!$B$8 -> EnergyWave, Inc. | D12: =Monthly!$C$8 -> Payroll | E12: =Monthly!$D$8 -> Salary & load | F12: =Monthly!$A$8 -> Founder & CEO | G12: =Monthly!P$8 -> 24400 | H12: =ScenarioName -> Base
A13: 12 | B13: =EDATE(StartDate,A13-1) -> 46722 | C13: =Monthly!$B$8 -> EnergyWave, Inc. | D13: =Monthly!$C$8 -> Payroll | E13: =Monthly!$D$8 -> Salary & load | F13: =Monthly!$A$8 -> Founder & CEO | G13: =Monthly!Q$8 -> 24400 | H13: =ScenarioName -> Base
A14: 13 | B14: =EDATE(StartDate,A14-1) -> 46753 | C14: =Monthly!$B$8 -> EnergyWave, Inc. | D14: =Monthly!$C$8 -> Payroll | E14: =Monthly!$D$8 -> Salary & load | F14: =Monthly!$A$8 -> Founder & CEO | G14: =Monthly!R$8 -> 24400 | H14: =ScenarioName -> Base
A15: 14 | B15: =EDATE(StartDate,A15-1) -> 46784 | C15: =Monthly!$B$8 -> EnergyWave, Inc. | D15: =Monthly!$C$8 -> Payroll | E15: =Monthly!$D$8 -> Salary & load | F15: =Monthly!$A$8 -> Founder & CEO | G15: =Monthly!S$8 -> 24400 | H15: =ScenarioName -> Base
A16: 15 | B16: =EDATE(StartDate,A16-1) -> 46813 | C16: =Monthly!$B$8 -> EnergyWave, Inc. | D16: =Monthly!$C$8 -> Payroll | E16: =Monthly!$D$8 -> Salary & load | F16: =Monthly!$A$8 -> Founder & CEO | G16: =Monthly!T$8 -> 24400 | H16: =ScenarioName -> Base
A17: 16 | B17: =EDATE(StartDate,A17-1) -> 46844 | C17: =Monthly!$B$8 -> EnergyWave, Inc. | D17: =Monthly!$C$8 -> Payroll | E17: =Monthly!$D$8 -> Salary & load | F17: =Monthly!$A$8 -> Founder & CEO | G17: =Monthly!U$8 -> 24400 | H17: =ScenarioName -> Base
A18: 17 | B18: =EDATE(StartDate,A18-1) -> 46874 | C18: =Monthly!$B$8 -> EnergyWave, Inc. | D18: =Monthly!$C$8 -> Payroll | E18: =Monthly!$D$8 -> Salary & load | F18: =Monthly!$A$8 -> Founder & CEO | G18: =Monthly!V$8 -> 24400 | H18: =ScenarioName -> Base
A19: 18 | B19: =EDATE(StartDate,A19-1) -> 46905 | C19: =Monthly!$B$8 -> EnergyWave, Inc. | D19: =Monthly!$C$8 -> Payroll | E19: =Monthly!$D$8 -> Salary & load | F19: =Monthly!$A$8 -> Founder & CEO | G19: =Monthly!W$8 -> 24400 | H19: =ScenarioName -> Base
A20: 19 | B20: =EDATE(StartDate,A20-1) -> 46935 | C20: =Monthly!$B$8 -> EnergyWave, Inc. | D20: =Monthly!$C$8 -> Payroll | E20: =Monthly!$D$8 -> Salary & load | F20: =Monthly!$A$8 -> Founder & CEO | G20: =Monthly!X$8 -> 24400 | H20: =ScenarioName -> Base
A21: 20 | B21: =EDATE(StartDate,A21-1) -> 46966 | C21: =Monthly!$B$8 -> EnergyWave, Inc. | D21: =Monthly!$C$8 -> Payroll | E21: =Monthly!$D$8 -> Salary & load | F21: =Monthly!$A$8 -> Founder & CEO | G21: =Monthly!Y$8 -> 24400 | H21: =ScenarioName -> Base
A22: 21 | B22: =EDATE(StartDate,A22-1) -> 46997 | C22: =Monthly!$B$8 -> EnergyWave, Inc. | D22: =Monthly!$C$8 -> Payroll | E22: =Monthly!$D$8 -> Salary & load | F22: =Monthly!$A$8 -> Founder & CEO | G22: =Monthly!Z$8 -> 24400 | H22: =ScenarioName -> Base
A23: 22 | B23: =EDATE(StartDate,A23-1) -> 47027 | C23: =Monthly!$B$8 -> EnergyWave, Inc. | D23: =Monthly!$C$8 -> Payroll | E23: =Monthly!$D$8 -> Salary & load | F23: =Monthly!$A$8 -> Founder & CEO | G23: =Monthly!AA$8 -> 24400 | H23: =ScenarioName -> Base
A24: 23 | B24: =EDATE(StartDate,A24-1) -> 47058 | C24: =Monthly!$B$8 -> EnergyWave, Inc. | D24: =Monthly!$C$8 -> Payroll | E24: =Monthly!$D$8 -> Salary & load | F24: =Monthly!$A$8 -> Founder & CEO | G24: =Monthly!AB$8 -> 24400 | H24: =ScenarioName -> Base
A25: 24 | B25: =EDATE(StartDate,A25-1) -> 47088 | C25: =Monthly!$B$8 -> EnergyWave, Inc. | D25: =Monthly!$C$8 -> Payroll | E25: =Monthly!$D$8 -> Salary & load | F25: =Monthly!$A$8 -> Founder & CEO | G25: =Monthly!AC$8 -> 24400 | H25: =ScenarioName -> Base
A26: 25 | B26: =EDATE(StartDate,A26-1) -> 47119 | C26: =Monthly!$B$8 -> EnergyWave, Inc. | D26: =Monthly!$C$8 -> Payroll | E26: =Monthly!$D$8 -> Salary & load | F26: =Monthly!$A$8 -> Founder & CEO | G26: =Monthly!AD$8 -> 24400 | H26: =ScenarioName -> Base
A27: 26 | B27: =EDATE(StartDate,A27-1) -> 47150 | C27: =Monthly!$B$8 -> EnergyWave, Inc. | D27: =Monthly!$C$8 -> Payroll | E27: =Monthly!$D$8 -> Salary & load | F27: =Monthly!$A$8 -> Founder & CEO | G27: =Monthly!AE$8 -> 24400 | H27: =ScenarioName -> Base
A28: 27 | B28: =EDATE(StartDate,A28-1) -> 47178 | C28: =Monthly!$B$8 -> EnergyWave, Inc. | D28: =Monthly!$C$8 -> Payroll | E28: =Monthly!$D$8 -> Salary & load | F28: =Monthly!$A$8 -> Founder & CEO | G28: =Monthly!AF$8 -> 24400 | H28: =ScenarioName -> Base
A29: 28 | B29: =EDATE(StartDate,A29-1) -> 47209 | C29: =Monthly!$B$8 -> EnergyWave, Inc. | D29: =Monthly!$C$8 -> Payroll | E29: =Monthly!$D$8 -> Salary & load | F29: =Monthly!$A$8 -> Founder & CEO | G29: =Monthly!AG$8 -> 24400 | H29: =ScenarioName -> Base
A30: 29 | B30: =EDATE(StartDate,A30-1) -> 47239 | C30: =Monthly!$B$8 -> EnergyWave, Inc. | D30: =Monthly!$C$8 -> Payroll | E30: =Monthly!$D$8 -> Salary & load | F30: =Monthly!$A$8 -> Founder & CEO | G30: =Monthly!AH$8 -> 24400 | H30: =ScenarioName -> Base
A31: 30 | B31: =EDATE(StartDate,A31-1) -> 47270 | C31: =Monthly!$B$8 -> EnergyWave, Inc. | D31: =Monthly!$C$8 -> Payroll | E31: =Monthly!$D$8 -> Salary & load | F31: =Monthly!$A$8 -> Founder & CEO | G31: =Monthly!AI$8 -> 24400 | H31: =ScenarioName -> Base
A32: 31 | B32: =EDATE(StartDate,A32-1) -> 47300 | C32: =Monthly!$B$8 -> EnergyWave, Inc. | D32: =Monthly!$C$8 -> Payroll | E32: =Monthly!$D$8 -> Salary & load | F32: =Monthly!$A$8 -> Founder & CEO | G32: =Monthly!AJ$8 -> 24400 | H32: =ScenarioName -> Base
A33: 32 | B33: =EDATE(StartDate,A33-1) -> 47331 | C33: =Monthly!$B$8 -> EnergyWave, Inc. | D33: =Monthly!$C$8 -> Payroll | E33: =Monthly!$D$8 -> Salary & load | F33: =Monthly!$A$8 -> Founder & CEO | G33: =Monthly!AK$8 -> 24400 | H33: =ScenarioName -> Base
A34: 33 | B34: =EDATE(StartDate,A34-1) -> 47362 | C34: =Monthly!$B$8 -> EnergyWave, Inc. | D34: =Monthly!$C$8 -> Payroll | E34: =Monthly!$D$8 -> Salary & load | F34: =Monthly!$A$8 -> Founder & CEO | G34: =Monthly!AL$8 -> 24400 | H34: =ScenarioName -> Base
A35: 34 | B35: =EDATE(StartDate,A35-1) -> 47392 | C35: =Monthly!$B$8 -> EnergyWave, Inc. | D35: =Monthly!$C$8 -> Payroll | E35: =Monthly!$D$8 -> Salary & load | F35: =Monthly!$A$8 -> Founder & CEO | G35: =Monthly!AM$8 -> 24400 | H35: =ScenarioName -> Base
A36: 35 | B36: =EDATE(StartDate,A36-1) -> 47423 | C36: =Monthly!$B$8 -> EnergyWave, Inc. | D36: =Monthly!$C$8 -> Payroll | E36: =Monthly!$D$8 -> Salary & load | F36: =Monthly!$A$8 -> Founder & CEO | G36: =Monthly!AN$8 -> 24400 | H36: =ScenarioName -> Base
A37: 36 | B37: =EDATE(StartDate,A37-1) -> 47453 | C37: =Monthly!$B$8 -> EnergyWave, Inc. | D37: =Monthly!$C$8 -> Payroll | E37: =Monthly!$D$8 -> Salary & load | F37: =Monthly!$A$8 -> Founder & CEO | G37: =Monthly!AO$8 -> 24400 | H37: =ScenarioName -> Base
A38: 1 | B38: =EDATE(StartDate,A38-1) -> 46388 | C38: =Monthly!$B$9 -> EnergyWave, Inc. | D38: =Monthly!$C$9 -> Consulting | E38: =Monthly!$D$9 -> Consulting fee | F38: =Monthly!$A$9 -> Co-founder / Research Director (part-time) | G38: =Monthly!F$9 -> 12500 | H38: =ScenarioName -> Base
A39: 2 | B39: =EDATE(StartDate,A39-1) -> 46419 | C39: =Monthly!$B$9 -> EnergyWave, Inc. | D39: =Monthly!$C$9 -> Consulting | E39: =Monthly!$D$9 -> Consulting fee | F39: =Monthly!$A$9 -> Co-founder / Research Director (part-time) | G39: =Monthly!G$9 -> 12500 | H39: =ScenarioName -> Base
A40: 3 | B40: =EDATE(StartDate,A40-1) -> 46447 | C40: =Monthly!$B$9 -> EnergyWave, Inc. | D40: =Monthly!$C$9 -> Consulting | E40: =Monthly!$D$9 -> Consulting fee | F40: =Monthly!$A$9 -> Co-founder / Research Director (part-time) | G40: =Monthly!H$9 -> 12500 | H40: =ScenarioName -> Base
A41: 4 | B41: =EDATE(StartDate,A41-1) -> 46478 | C41: =Monthly!$B$9 -> EnergyWave, Inc. | D41: =Monthly!$C$9 -> Consulting | E41: =Monthly!$D$9 -> Consulting fee | F41: =Monthly!$A$9 -> Co-founder / Research Director (part-time) | G41: =Monthly!I$9 -> 12500 | H41: =ScenarioName -> Base
A42: 5 | B42: =EDATE(StartDate,A42-1) -> 46508 | C42: =Monthly!$B$9 -> EnergyWave, Inc. | D42: =Monthly!$C$9 -> Consulting | E42: =Monthly!$D$9 -> Consulting fee | F42: =Monthly!$A$9 -> Co-founder / Research Director (part-time) | G42: =Monthly!J$9 -> 12500 | H42: =ScenarioName -> Base
A43: 6 | B43: =EDATE(StartDate,A43-1) -> 46539 | C43: =Monthly!$B$9 -> EnergyWave, Inc. | D43: =Monthly!$C$9 -> Consulting | E43: =Monthly!$D$9 -> Consulting fee | F43: =Monthly!$A$9 -> Co-founder / Research Director (part-time) | G43: =Monthly!K$9 -> 12500 | H43: =ScenarioName -> Base
A44: 7 | B44: =EDATE(StartDate,A44-1) -> 46569 | C44: =Monthly!$B$9 -> EnergyWave, Inc. | D44: =Monthly!$C$9 -> Consulting | E44: =Monthly!$D$9 -> Consulting fee | F44: =Monthly!$A$9 -> Co-founder / Research Director (part-time) | G44: =Monthly!L$9 -> 12500 | H44: =ScenarioName -> Base
A45: 8 | B45: =EDATE(StartDate,A45-1) -> 46600 | C45: =Monthly!$B$9 -> EnergyWave, Inc. | D45: =Monthly!$C$9 -> Consulting | E45: =Monthly!$D$9 -> Consulting fee | F45: =Monthly!$A$9 -> Co-founder / Research Director (part-time) | G45: =Monthly!M$9 -> 12500 | H45: =ScenarioName -> Base
A46: 9 | B46: =EDATE(StartDate,A46-1) -> 46631 | C46: =Monthly!$B$9 -> EnergyWave, Inc. | D46: =Monthly!$C$9 -> Consulting | E46: =Monthly!$D$9 -> Consulting fee | F46: =Monthly!$A$9 -> Co-founder / Research Director (part-time) | G46: =Monthly!N$9 -> 12500 | H46: =ScenarioName -> Base
A47: 10 | B47: =EDATE(StartDate,A47-1) -> 46661 | C47: =Monthly!$B$9 -> EnergyWave, Inc. | D47: =Monthly!$C$9 -> Consulting | E47: =Monthly!$D$9 -> Consulting fee | F47: =Monthly!$A$9 -> Co-founder / Research Director (part-time) | G47: =Monthly!O$9 -> 12500 | H47: =ScenarioName -> Base
A48: 11 | B48: =EDATE(StartDate,A48-1) -> 46692 | C48: =Monthly!$B$9 -> EnergyWave, Inc. | D48: =Monthly!$C$9 -> Consulting | E48: =Monthly!$D$9 -> Consulting fee | F48: =Monthly!$A$9 -> Co-founder / Research Director (part-time) | G48: =Monthly!P$9 -> 12500 | H48: =ScenarioName -> Base
A49: 12 | B49: =EDATE(StartDate,A49-1) -> 46722 | C49: =Monthly!$B$9 -> EnergyWave, Inc. | D49: =Monthly!$C$9 -> Consulting | E49: =Monthly!$D$9 -> Consulting fee | F49: =Monthly!$A$9 -> Co-founder / Research Director (part-time) | G49: =Monthly!Q$9 -> 12500 | H49: =ScenarioName -> Base
A50: 13 | B50: =EDATE(StartDate,A50-1) -> 46753 | C50: =Monthly!$B$9 -> EnergyWave, Inc. | D50: =Monthly!$C$9 -> Consulting | E50: =Monthly!$D$9 -> Consulting fee | F50: =Monthly!$A$9 -> Co-founder / Research Director (part-time) | G50: =Monthly!R$9 -> 12500 | H50: =ScenarioName -> Base
A51: 14 | B51: =EDATE(StartDate,A51-1) -> 46784 | C51: =Monthly!$B$9 -> EnergyWave, Inc. | D51: =Monthly!$C$9 -> Consulting | E51: =Monthly!$D$9 -> Consulting fee | F51: =Monthly!$A$9 -> Co-founder / Research Director (part-time) | G51: =Monthly!S$9 -> 12500 | H51: =ScenarioName -> Base
A52: 15 | B52: =EDATE(StartDate,A52-1) -> 46813 | C52: =Monthly!$B$9 -> EnergyWave, Inc. | D52: =Monthly!$C$9 -> Consulting | E52: =Monthly!$D$9 -> Consulting fee | F52: =Monthly!$A$9 -> Co-founder / Research Director (part-time) | G52: =Monthly!T$9 -> 12500 | H52: =ScenarioName -> Base
A53: 16 | B53: =EDATE(StartDate,A53-1) -> 46844 | C53: =Monthly!$B$9 -> EnergyWave, Inc. | D53: =Monthly!$C$9 -> Consulting | E53: =Monthly!$D$9 -> Consulting fee | F53: =Monthly!$A$9 -> Co-founder / Research Director (part-time) | G53: =Monthly!U$9 -> 12500 | H53: =ScenarioName -> Base
A54: 17 | B54: =EDATE(StartDate,A54-1) -> 46874 | C54: =Monthly!$B$9 -> EnergyWave, Inc. | D54: =Monthly!$C$9 -> Consulting | E54: =Monthly!$D$9 -> Consulting fee | F54: =Monthly!$A$9 -> Co-founder / Research Director (part-time) | G54: =Monthly!V$9 -> 12500 | H54: =ScenarioName -> Base
A55: 18 | B55: =EDATE(StartDate,A55-1) -> 46905 | C55: =Monthly!$B$9 -> EnergyWave, Inc. | D55: =Monthly!$C$9 -> Consulting | E55: =Monthly!$D$9 -> Consulting fee | F55: =Monthly!$A$9 -> Co-founder / Research Director (part-time) | G55: =Monthly!W$9 -> 12500 | H55: =ScenarioName -> Base
A56: 19 | B56: =EDATE(StartDate,A56-1) -> 46935 | C56: =Monthly!$B$9 -> EnergyWave, Inc. | D56: =Monthly!$C$9 -> Consulting | E56: =Monthly!$D$9 -> Consulting fee | F56: =Monthly!$A$9 -> Co-founder / Research Director (part-time) | G56: =Monthly!X$9 -> 12500 | H56: =ScenarioName -> Base
A57: 20 | B57: =EDATE(StartDate,A57-1) -> 46966 | C57: =Monthly!$B$9 -> EnergyWave, Inc. | D57: =Monthly!$C$9 -> Consulting | E57: =Monthly!$D$9 -> Consulting fee | F57: =Monthly!$A$9 -> Co-founder / Research Director (part-time) | G57: =Monthly!Y$9 -> 12500 | H57: =ScenarioName -> Base
A58: 21 | B58: =EDATE(StartDate,A58-1) -> 46997 | C58: =Monthly!$B$9 -> EnergyWave, Inc. | D58: =Monthly!$C$9 -> Consulting | E58: =Monthly!$D$9 -> Consulting fee | F58: =Monthly!$A$9 -> Co-founder / Research Director (part-time) | G58: =Monthly!Z$9 -> 12500 | H58: =ScenarioName -> Base
A59: 22 | B59: =EDATE(StartDate,A59-1) -> 47027 | C59: =Monthly!$B$9 -> EnergyWave, Inc. | D59: =Monthly!$C$9 -> Consulting | E59: =Monthly!$D$9 -> Consulting fee | F59: =Monthly!$A$9 -> Co-founder / Research Director (part-time) | G59: =Monthly!AA$9 -> 12500 | H59: =ScenarioName -> Base
A60: 23 | B60: =EDATE(StartDate,A60-1) -> 47058 | C60: =Monthly!$B$9 -> EnergyWave, Inc. | D60: =Monthly!$C$9 -> Consulting | E60: =Monthly!$D$9 -> Consulting fee | F60: =Monthly!$A$9 -> Co-founder / Research Director (part-time) | G60: =Monthly!AB$9 -> 12500 | H60: =ScenarioName -> Base
A61: 24 | B61: =EDATE(StartDate,A61-1) -> 47088 | C61: =Monthly!$B$9 -> EnergyWave, Inc. | D61: =Monthly!$C$9 -> Consulting | E61: =Monthly!$D$9 -> Consulting fee | F61: =Monthly!$A$9 -> Co-founder / Research Director (part-time) | G61: =Monthly!AC$9 -> 12500 | H61: =ScenarioName -> Base
A62: 25 | B62: =EDATE(StartDate,A62-1) -> 47119 | C62: =Monthly!$B$9 -> EnergyWave, Inc. | D62: =Monthly!$C$9 -> Consulting | E62: =Monthly!$D$9 -> Consulting fee | F62: =Monthly!$A$9 -> Co-founder / Research Director (part-time) | G62: =Monthly!AD$9 -> 12500 | H62: =ScenarioName -> Base
A63: 26 | B63: =EDATE(StartDate,A63-1) -> 47150 | C63: =Monthly!$B$9 -> EnergyWave, Inc. | D63: =Monthly!$C$9 -> Consulting | E63: =Monthly!$D$9 -> Consulting fee | F63: =Monthly!$A$9 -> Co-founder / Research Director (part-time) | G63: =Monthly!AE$9 -> 12500 | H63: =ScenarioName -> Base
A64: 27 | B64: =EDATE(StartDate,A64-1) -> 47178 | C64: =Monthly!$B$9 -> EnergyWave, Inc. | D64: =Monthly!$C$9 -> Consulting | E64: =Monthly!$D$9 -> Consulting fee | F64: =Monthly!$A$9 -> Co-founder / Research Director (part-time) | G64: =Monthly!AF$9 -> 12500 | H64: =ScenarioName -> Base
A65: 28 | B65: =EDATE(StartDate,A65-1) -> 47209 | C65: =Monthly!$B$9 -> EnergyWave, Inc. | D65: =Monthly!$C$9 -> Consulting | E65: =Monthly!$D$9 -> Consulting fee | F65: =Monthly!$A$9 -> Co-founder / Research Director (part-time) | G65: =Monthly!AG$9 -> 12500 | H65: =ScenarioName -> Base
A66: 29 | B66: =EDATE(StartDate,A66-1) -> 47239 | C66: =Monthly!$B$9 -> EnergyWave, Inc. | D66: =Monthly!$C$9 -> Consulting | E66: =Monthly!$D$9 -> Consulting fee | F66: =Monthly!$A$9 -> Co-founder / Research Director (part-time) | G66: =Monthly!AH$9 -> 12500 | H66: =ScenarioName -> Base
A67: 30 | B67: =EDATE(StartDate,A67-1) -> 47270 | C67: =Monthly!$B$9 -> EnergyWave, Inc. | D67: =Monthly!$C$9 -> Consulting | E67: =Monthly!$D$9 -> Consulting fee | F67: =Monthly!$A$9 -> Co-founder / Research Director (part-time) | G67: =Monthly!AI$9 -> 12500 | H67: =ScenarioName -> Base
A68: 31 | B68: =EDATE(StartDate,A68-1) -> 47300 | C68: =Monthly!$B$9 -> EnergyWave, Inc. | D68: =Monthly!$C$9 -> Consulting | E68: =Monthly!$D$9 -> Consulting fee | F68: =Monthly!$A$9 -> Co-founder / Research Director (part-time) | G68: =Monthly!AJ$9 -> 12500 | H68: =ScenarioName -> Base
A69: 32 | B69: =EDATE(StartDate,A69-1) -> 47331 | C69: =Monthly!$B$9 -> EnergyWave, Inc. | D69: =Monthly!$C$9 -> Consulting | E69: =Monthly!$D$9 -> Consulting fee | F69: =Monthly!$A$9 -> Co-founder / Research Director (part-time) | G69: =Monthly!AK$9 -> 12500 | H69: =ScenarioName -> Base
A70: 33 | B70: =EDATE(StartDate,A70-1) -> 47362 | C70: =Monthly!$B$9 -> EnergyWave, Inc. | D70: =Monthly!$C$9 -> Consulting | E70: =Monthly!$D$9 -> Consulting fee | F70: =Monthly!$A$9 -> Co-founder / Research Director (part-time) | G70: =Monthly!AL$9 -> 12500 | H70: =ScenarioName -> Base
A71: 34 | B71: =EDATE(StartDate,A71-1) -> 47392 | C71: =Monthly!$B$9 -> EnergyWave, Inc. | D71: =Monthly!$C$9 -> Consulting | E71: =Monthly!$D$9 -> Consulting fee | F71: =Monthly!$A$9 -> Co-founder / Research Director (part-time) | G71: =Monthly!AM$9 -> 12500 | H71: =ScenarioName -> Base
A72: 35 | B72: =EDATE(StartDate,A72-1) -> 47423 | C72: =Monthly!$B$9 -> EnergyWave, Inc. | D72: =Monthly!$C$9 -> Consulting | E72: =Monthly!$D$9 -> Consulting fee | F72: =Monthly!$A$9 -> Co-founder / Research Director (part-time) | G72: =Monthly!AN$9 -> 12500 | H72: =ScenarioName -> Base
A73: 36 | B73: =EDATE(StartDate,A73-1) -> 47453 | C73: =Monthly!$B$9 -> EnergyWave, Inc. | D73: =Monthly!$C$9 -> Consulting | E73: =Monthly!$D$9 -> Consulting fee | F73: =Monthly!$A$9 -> Co-founder / Research Director (part-time) | G73: =Monthly!AO$9 -> 12500 | H73: =ScenarioName -> Base
A74: 1 | B74: =EDATE(StartDate,A74-1) -> 46388 | C74: =Monthly!$B$10 -> EnergyWave, Inc. | D74: =Monthly!$C$10 -> Payroll | E74: =Monthly!$D$10 -> Salary & load | F74: =Monthly!$A$10 -> Applied Physicist 1 | G74: =Monthly!F$10 -> 0 | H74: =ScenarioName -> Base
A75: 2 | B75: =EDATE(StartDate,A75-1) -> 46419 | C75: =Monthly!$B$10 -> EnergyWave, Inc. | D75: =Monthly!$C$10 -> Payroll | E75: =Monthly!$D$10 -> Salary & load | F75: =Monthly!$A$10 -> Applied Physicist 1 | G75: =Monthly!G$10 -> 15250 | H75: =ScenarioName -> Base
A76: 3 | B76: =EDATE(StartDate,A76-1) -> 46447 | C76: =Monthly!$B$10 -> EnergyWave, Inc. | D76: =Monthly!$C$10 -> Payroll | E76: =Monthly!$D$10 -> Salary & load | F76: =Monthly!$A$10 -> Applied Physicist 1 | G76: =Monthly!H$10 -> 15250 | H76: =ScenarioName -> Base
A77: 4 | B77: =EDATE(StartDate,A77-1) -> 46478 | C77: =Monthly!$B$10 -> EnergyWave, Inc. | D77: =Monthly!$C$10 -> Payroll | E77: =Monthly!$D$10 -> Salary & load | F77: =Monthly!$A$10 -> Applied Physicist 1 | G77: =Monthly!I$10 -> 15250 | H77: =ScenarioName -> Base
A78: 5 | B78: =EDATE(StartDate,A78-1) -> 46508 | C78: =Monthly!$B$10 -> EnergyWave, Inc. | D78: =Monthly!$C$10 -> Payroll | E78: =Monthly!$D$10 -> Salary & load | F78: =Monthly!$A$10 -> Applied Physicist 1 | G78: =Monthly!J$10 -> 15250 | H78: =ScenarioName -> Base
A79: 6 | B79: =EDATE(StartDate,A79-1) -> 46539 | C79: =Monthly!$B$10 -> EnergyWave, Inc. | D79: =Monthly!$C$10 -> Payroll | E79: =Monthly!$D$10 -> Salary & load | F79: =Monthly!$A$10 -> Applied Physicist 1 | G79: =Monthly!K$10 -> 15250 | H79: =ScenarioName -> Base
A80: 7 | B80: =EDATE(StartDate,A80-1) -> 46569 | C80: =Monthly!$B$10 -> EnergyWave, Inc. | D80: =Monthly!$C$10 -> Payroll | E80: =Monthly!$D$10 -> Salary & load | F80: =Monthly!$A$10 -> Applied Physicist 1 | G80: =Monthly!L$10 -> 15250 | H80: =ScenarioName -> Base
A81: 8 | B81: =EDATE(StartDate,A81-1) -> 46600 | C81: =Monthly!$B$10 -> EnergyWave, Inc. | D81: =Monthly!$C$10 -> Payroll | E81: =Monthly!$D$10 -> Salary & load | F81: =Monthly!$A$10 -> Applied Physicist 1 | G81: =Monthly!M$10 -> 15250 | H81: =ScenarioName -> Base
A82: 9 | B82: =EDATE(StartDate,A82-1) -> 46631 | C82: =Monthly!$B$10 -> EnergyWave, Inc. | D82: =Monthly!$C$10 -> Payroll | E82: =Monthly!$D$10 -> Salary & load | F82: =Monthly!$A$10 -> Applied Physicist 1 | G82: =Monthly!N$10 -> 15250 | H82: =ScenarioName -> Base
A83: 10 | B83: =EDATE(StartDate,A83-1) -> 46661 | C83: =Monthly!$B$10 -> EnergyWave, Inc. | D83: =Monthly!$C$10 -> Payroll | E83: =Monthly!$D$10 -> Salary & load | F83: =Monthly!$A$10 -> Applied Physicist 1 | G83: =Monthly!O$10 -> 15250 | H83: =ScenarioName -> Base
A84: 11 | B84: =EDATE(StartDate,A84-1) -> 46692 | C84: =Monthly!$B$10 -> EnergyWave, Inc. | D84: =Monthly!$C$10 -> Payroll | E84: =Monthly!$D$10 -> Salary & load | F84: =Monthly!$A$10 -> Applied Physicist 1 | G84: =Monthly!P$10 -> 15250 | H84: =ScenarioName -> Base
A85: 12 | B85: =EDATE(StartDate,A85-1) -> 46722 | C85: =Monthly!$B$10 -> EnergyWave, Inc. | D85: =Monthly!$C$10 -> Payroll | E85: =Monthly!$D$10 -> Salary & load | F85: =Monthly!$A$10 -> Applied Physicist 1 | G85: =Monthly!Q$10 -> 15250 | H85: =ScenarioName -> Base
A86: 13 | B86: =EDATE(StartDate,A86-1) -> 46753 | C86: =Monthly!$B$10 -> EnergyWave, Inc. | D86: =Monthly!$C$10 -> Payroll | E86: =Monthly!$D$10 -> Salary & load | F86: =Monthly!$A$10 -> Applied Physicist 1 | G86: =Monthly!R$10 -> 15250 | H86: =ScenarioName -> Base
A87: 14 | B87: =EDATE(StartDate,A87-1) -> 46784 | C87: =Monthly!$B$10 -> EnergyWave, Inc. | D87: =Monthly!$C$10 -> Payroll | E87: =Monthly!$D$10 -> Salary & load | F87: =Monthly!$A$10 -> Applied Physicist 1 | G87: =Monthly!S$10 -> 15250 | H87: =ScenarioName -> Base
A88: 15 | B88: =EDATE(StartDate,A88-1) -> 46813 | C88: =Monthly!$B$10 -> EnergyWave, Inc. | D88: =Monthly!$C$10 -> Payroll | E88: =Monthly!$D$10 -> Salary & load | F88: =Monthly!$A$10 -> Applied Physicist 1 | G88: =Monthly!T$10 -> 15250 | H88: =ScenarioName -> Base
A89: 16 | B89: =EDATE(StartDate,A89-1) -> 46844 | C89: =Monthly!$B$10 -> EnergyWave, Inc. | D89: =Monthly!$C$10 -> Payroll | E89: =Monthly!$D$10 -> Salary & load | F89: =Monthly!$A$10 -> Applied Physicist 1 | G89: =Monthly!U$10 -> 15250 | H89: =ScenarioName -> Base
A90: 17 | B90: =EDATE(StartDate,A90-1) -> 46874 | C90: =Monthly!$B$10 -> EnergyWave, Inc. | D90: =Monthly!$C$10 -> Payroll | E90: =Monthly!$D$10 -> Salary & load | F90: =Monthly!$A$10 -> Applied Physicist 1 | G90: =Monthly!V$10 -> 15250 | H90: =ScenarioName -> Base
A91: 18 | B91: =EDATE(StartDate,A91-1) -> 46905 | C91: =Monthly!$B$10 -> EnergyWave, Inc. | D91: =Monthly!$C$10 -> Payroll | E91: =Monthly!$D$10 -> Salary & load | F91: =Monthly!$A$10 -> Applied Physicist 1 | G91: =Monthly!W$10 -> 15250 | H91: =ScenarioName -> Base
A92: 19 | B92: =EDATE(StartDate,A92-1) -> 46935 | C92: =Monthly!$B$10 -> EnergyWave, Inc. | D92: =Monthly!$C$10 -> Payroll | E92: =Monthly!$D$10 -> Salary & load | F92: =Monthly!$A$10 -> Applied Physicist 1 | G92: =Monthly!X$10 -> 15250 | H92: =ScenarioName -> Base
A93: 20 | B93: =EDATE(StartDate,A93-1) -> 46966 | C93: =Monthly!$B$10 -> EnergyWave, Inc. | D93: =Monthly!$C$10 -> Payroll | E93: =Monthly!$D$10 -> Salary & load | F93: =Monthly!$A$10 -> Applied Physicist 1 | G93: =Monthly!Y$10 -> 15250 | H93: =ScenarioName -> Base
A94: 21 | B94: =EDATE(StartDate,A94-1) -> 46997 | C94: =Monthly!$B$10 -> EnergyWave, Inc. | D94: =Monthly!$C$10 -> Payroll | E94: =Monthly!$D$10 -> Salary & load | F94: =Monthly!$A$10 -> Applied Physicist 1 | G94: =Monthly!Z$10 -> 15250 | H94: =ScenarioName -> Base
A95: 22 | B95: =EDATE(StartDate,A95-1) -> 47027 | C95: =Monthly!$B$10 -> EnergyWave, Inc. | D95: =Monthly!$C$10 -> Payroll | E95: =Monthly!$D$10 -> Salary & load | F95: =Monthly!$A$10 -> Applied Physicist 1 | G95: =Monthly!AA$10 -> 15250 | H95: =ScenarioName -> Base
A96: 23 | B96: =EDATE(StartDate,A96-1) -> 47058 | C96: =Monthly!$B$10 -> EnergyWave, Inc. | D96: =Monthly!$C$10 -> Payroll | E96: =Monthly!$D$10 -> Salary & load | F96: =Monthly!$A$10 -> Applied Physicist 1 | G96: =Monthly!AB$10 -> 15250 | H96: =ScenarioName -> Base
A97: 24 | B97: =EDATE(StartDate,A97-1) -> 47088 | C97: =Monthly!$B$10 -> EnergyWave, Inc. | D97: =Monthly!$C$10 -> Payroll | E97: =Monthly!$D$10 -> Salary & load | F97: =Monthly!$A$10 -> Applied Physicist 1 | G97: =Monthly!AC$10 -> 15250 | H97: =ScenarioName -> Base
A98: 25 | B98: =EDATE(StartDate,A98-1) -> 47119 | C98: =Monthly!$B$10 -> EnergyWave, Inc. | D98: =Monthly!$C$10 -> Payroll | E98: =Monthly!$D$10 -> Salary & load | F98: =Monthly!$A$10 -> Applied Physicist 1 | G98: =Monthly!AD$10 -> 15250 | H98: =ScenarioName -> Base
A99: 26 | B99: =EDATE(StartDate,A99-1) -> 47150 | C99: =Monthly!$B$10 -> EnergyWave, Inc. | D99: =Monthly!$C$10 -> Payroll | E99: =Monthly!$D$10 -> Salary & load | F99: =Monthly!$A$10 -> Applied Physicist 1 | G99: =Monthly!AE$10 -> 15250 | H99: =ScenarioName -> Base
A100: 27 | B100: =EDATE(StartDate,A100-1) -> 47178 | C100: =Monthly!$B$10 -> EnergyWave, Inc. | D100: =Monthly!$C$10 -> Payroll | E100: =Monthly!$D$10 -> Salary & load | F100: =Monthly!$A$10 -> Applied Physicist 1 | G100: =Monthly!AF$10 -> 15250 | H100: =ScenarioName -> Base
...

Sheet Entities
A1: Entity & funds-flow map
A2: One row per entity in the structure plus the escrow counterparty. 'Control that must exist' is the diligence test for each.
A3: Entity | B3: Form / jurisdiction | C3: Purpose | D3: Relationship to EnergyWave, Inc. | E3: Funded by | F3: Planned flows with EnergyWave | G3: Control that must exist | H3: Counsel | I3: Status / open item
A4: EnergyWave, Inc. | B4: Delaware C-corp (in formation, K&L Gates) | C4: Research venture: portable high-energy-density power for humanoid robotics; three-gate conservation-of-energy protocol with mandatory null-result publication | D4: Operating company — this raise | E4: Next raise (this model) | F4: Receives transitional services from McLean Companies; arms-length services with the nonprofits only | G4: Claims discipline on every document; IP assignment from founders and McLean Companies; 409A; option pool; board & advisor agreements | H4: K&L Gates (Novak, Majewski); Johnson (securities) | I4: Formation in progress
A5: GovThink Institute (govthink.org) | B5: 501(c)(3) (in formation) | C5: Policy institute: government engagement, dual-use release frameworks, tech-transfer policy, null-results registry, safety advocacy | D5: Affiliated nonprofit; Ian is founder of both — disclosed on govthink.org | E5: Donations / grants — NOT this raise | F5: Any services priced at fair market value under written agreement; no EW cost shifted to the nonprofit | G5: Private benefit / inurement (IRC §501(c)(3), §4958): independent board majority, conflict-of-interest policy, the nine mitigations in the counsel package | H5: K&L Gates | I5: Determination pending; donation-solicitation question with Brian — BLOCKED
A6: pinnacle.blog | B6: Nonprofit (per Ian — confirm form, state, and status) | C6: TBD — confirm mission | D6: TBD — confirm relationship to EW and to GovThink | E6: Donations / grants — NOT this raise | F6: None until documented | G6: A second affiliated nonprofit multiplies the private-benefit analysis; needs the same mitigations, its own board, and its own books | H6: TBD | I6: NEED: mission, formation documents, board, relationship memo
A7: [Wyoming LLC — name TBD] | B7: Wyoming LLC holding company (investor pooling vehicle) | C7: Aggregates smaller shareholders into one line on the EW cap table | D7: Shareholder of EnergyWave, Inc. | E7: Investor capital (flows into the raise) | F7: Invests into EW; no operating flows | G7: Securities structure: Reg D, Investment Company Act exemption, blue-sky filings; who manages it and for what fee; conflict disclosure if Ian manages a vehicle investing in his own company; look-through schedule in the packet | H7: Johnson (securities) | I7: NEED: name, manager, operating agreement, subscription documents
A8: McLean Companies LLC | B8: Established LLC (Ian's consulting entity) | C8: Operational history; letterhead for government-facing documents; paid pre-formation expenses | D8: Founder entity; transitional service provider | E8: Ian | F8: Reimbursement of documented pre-formation expenses; assignment of any EW-related IP and contracts to EW | G8: Related-party disclosure; written reimbursement agreement; IP/contract assignment; a stop date for the transitional arrangement | H8: K&L Gates | I8: NEED: pre-formation expense ledger and assignment agreement
A9: Escrow (investment bank — Andrew Low) | B9: Third-party escrow account | C9: Holds raise proceeds pending release conditions | D9: Counterparty — not controlled by Ian | E9: n/a | F9: Escrow → EW operating account on release conditions | G9: Escrow agreement in hand; escrow agent and bank confirmed directly with the bank; release conditions understood; no fee payable to release funds; engagement letter and fee schedule reviewed by counsel | H9: Johnson / Novak | I9: NEED: escrow agreement + direct bank confirmation before anyone bills against the raise

Sheet Roster
A1: Team, advisors, counsel & proposed vendors
A2: 'Verify before packet' lists bio or role claims that must be checked against primary sources. Nothing goes in the packet unverified.
A3: Name | B3: Role (per Ian) | C3: Entity / relationship | D3: Engagement type (proposed) | E3: Cash in model? | F3: LinkedIn | G3: Verify before packet | H3: Status
A4: Ian F. McLean | B4: Founder & CEO | C4: EnergyWave, Inc.; GovThink Institute; McLean Companies LLC | D4: Employee | E4: Yes — H01 | G4: Founder disclosures: outside investments (incl. the hydrogen company stake), McLean Companies related-party terms | H4: Founder
A5: Kenneth "Chip" Story | B5: Co-founder | C5: EnergyWave, Inc.; Director & R&T Team Leader, ZPEPG | D5: Part-time / consulting | E5: Yes — H02 | F5: linkedin.com/in/chipstorygeophysics | G5: Co-founder agreement and vesting; ZPEPG conflict/IP boundary; M.S. geophysics (Colorado School of Mines) | H5: Confirm terms
A6: Jack Sarfatti, Ph.D. | B6: Physics advisory (co-founder in earlier documents) | C6: Advisor | D6: Advisor agreement (equity) | E6: No | F6: linkedin.com/in/jack-sarfatti-47793b20 | G6: Bio wording: 'trained under Hans Bethe at Cornell; Ph.D. UC Riverside' — NOT 'Ph.D. under a Nobel laureate'. Omit the Altman neighbor reference. On-record skeptic of the premise = credibility asset; keep that in. | H6: Rewrite bio
A7: Alan Crunkleton, Ph.D., M.D. | B7: Second advisor (technical & financial) | C7: Advisor; Partner, Hardesty LLC | D7: Advisor agreement (equity) | E7: No | F7: linkedin.com/in/alancrunkleton | G7: On-record skeptic = asset. Confirm Hardesty affiliation wording. | H7: Confirm
A8: Mike Wentz | B8: Third advisor (vetting / diligence) | C8: Advisor | D8: Advisor agreement (equity) | E8: No | F8: linkedin.com/in/mike-wentz | G8: Credential discrepancy: Ian says bioengineering Ph.D.; LinkedIn lists M.S. Resolve before any document. | H8: Verify credential
A9: Andrew Low | B9: Investment bank; holds the escrow account | C9: Counterparty | D9: Engagement letter | E9: Fees TBD — not in model | F9: linkedin.com/in/andrewlow17 | G9: Firm identity; broker-dealer / FINRA registration; escrow agreement; escrow agent and bank confirmed directly; fee schedule; success-fee and expense terms | H9: Verify before reliance
A10: Craig Weaver | B10: Advisory accounting specialist | C10: Advisor / vendor | D10: TBD | E10: Not separately — outsourced-finance line (C17/C18) | F10: linkedin.com/in/craig-weaver-a704785 | G10: Define scope vs. E57 to avoid overlap; confirm licensure if attesting | H10: Define scope
A11: David Norris | B11: Tenured financier specialist | C11: Advisor | D11: Advisor agreement (equity) / TBD | E11: No | F11: linkedin.com/in/david-norris-660a87 | G11: Define role in the raise (placement, board, or advisory) | H11: Define role
A12: Eric Fitzgerald | B12: Government liaison | C12: Consultant | D12: Consulting agreement | E12: Yes — H18 | F12: linkedin.com/in/ericfoxfitzgerald | G12: Terms (cash vs. equity); lobbying-disclosure review if activity qualifies | H12: Confirm terms
A13: Joseph Johnson | B13: Securities & IP litigation counsel; class-action background (per Ian) | C13: Counsel | D13: Legal fees | E13: Yes — C15 | F13: linkedin.com/in/jkjohnson | G13: Previously kept off public-facing documents — confirm whether he appears in the packet at all | H13: Decide
A14: George Roth | B14: Legacy investment-banking advisory | C14: Advisor | D14: Advisor agreement (equity) / TBD | E14: No | F14: linkedin.com/in/georgeroth | G14: Define role vs. Andrew Low; avoid two banks with unclear mandates | H14: Define role
A15: Brian Novak | B15: K&L Gates, Irvine — entity formation & IP retainer | C15: Counsel | D15: Legal fees | E15: Yes — C13/C14 | G15: Precise title (Partner in Charge?) and Ph.D. reference — verify | H15: Verify title
A16: Dennis Majewski | B16: K&L Gates Partner — EE/CE, semiconductors, quantum circuits | C16: Counsel | D16: Legal fees | E16: Yes — C13 | H16: OK
A17: E57 Partners — Jonathan Wallace | B17: Interim FP&A (proposed) | C17: Vendor | D17: Consulting (E57 engagement) | E17: Yes — C17/C18 | G17: Who does the work; reference from a pre-revenue research venture; independence from the bank and investors | H17: Proposed
A18: E57 Partners — David McKee | B18: Interim Controller & FP&A (proposed) | C18: Vendor | D18: Consulting (E57 engagement) | E18: Yes — C17/C18 | G18: Multi-entity + nonprofit competence (Form 990, private-benefit rules); QuickBooks vs NetSuite recommendation | H18: Proposed
A19: E57 Partners — Alex Wells | B19: Interim CFO (optional, fractional) | C19: Vendor | D19: Consulting (fractional hours) | E19: Not modeled | G19: Only if a CFO name is needed with the bank / IQT | H19: Optional
A20: E57 Partners — Austin Griffin, CPA | B20: Interim Controller (SEC/SOX/ERP) | C20: Vendor | D20: — | E20: Not modeled | G20: Post-Series-A need; not now | H20: Defer
A21: E57 Partners — Joseph Kirchon, CPA (contact) | B21: CFO, East 57th Street Partners, Dallas | C21: Vendor contact | D21: — | E21: — | G21: Firm confirmed: founded 2014, Dallas, ~107 professionals, consulting/staffing/executive search in accounting, finance, HR, IT | H21: Verified

Sheet DD_Checklist
A1: Due-diligence packet — data-room index
A2: Status: Have / In progress / Need / Blocked. Owner is who produces it. Nothing enters the packet without the verification standard in the last column being met.
A3: # | B3: Section | C3: Item | D3: Owner | E3: Status | F3: Verification standard / notes
A4: 1 | B4: A. Corporate & governance | C4: Certificate of incorporation, bylaws, board consents — EnergyWave, Inc. | D4: Novak (K&L Gates) | E4: In progress
A5: 2 | B5: A. Corporate & governance | C5: Org chart of all five entities + funds-flow map | D5: Ian / E57 | E5: Have (draft) | F5: Entities sheet in this workbook; finalize once Wyoming LLC and pinnacle.blog are documented
A6: 3 | B6: A. Corporate & governance | C6: Intercompany / services agreements with GovThink Institute and pinnacle.blog | D6: Novak | E6: Blocked | F6: Arms-length, FMV pricing, written; nonprofit boards approve
A7: 4 | B7: A. Corporate & governance | C7: Board, advisor, and co-founder agreements with vesting | D7: Novak | E7: Need | F7: Every person on the Roster sheet
A8: 5 | B8: A. Corporate & governance | C8: Conflict-of-interest policy and founder disclosures (outside investments, McLean Companies terms) | D8: Ian / Novak | E8: Need | F8: Includes the hydrogen-company stake
A9: 6 | B9: B. Capitalization & securities | C9: Fully diluted cap table incl. option pool | D9: Johnson / E57 | E9: Need | F9: Option pool % per Assumptions; SPV shown as one line with look-through schedule
A10: 7 | B10: B. Capitalization & securities | C10: Pre-seed SAFE(s) and terms | D10: Ian | E10: Have
A11: 8 | B11: B. Capitalization & securities | C11: Wyoming pooling LLC: operating agreement, subscription docs, manager, fees, exemptions | D11: Johnson | E11: Need | F11: Reg D; Investment Company Act exemption; blue sky
A12: 9 | B12: B. Capitalization & securities | C12: 409A valuation | D12: E57 / valuation firm | E12: Need | F12: Before option grants
A13: 10 | B13: B. Capitalization & securities | C13: Escrow agreement, escrow agent identity, direct bank confirmation, release conditions | D13: Ian / Johnson | E13: Need | F13: Confirmed with the bank directly, not via the introducer; no fee to release funds
A14: 11 | B14: B. Capitalization & securities | C14: Investment bank engagement letter and fee schedule (Andrew Low) | D14: Ian / Johnson | E14: Need | F14: Broker-dealer registration verified
A15: 12 | B15: B. Capitalization & securities | C15: Reg D / blue-sky filings for the raise | D15: Johnson | E15: Need
A16: 13 | B16: C. Team | C16: Bios with every claim verified | D16: Ian | E16: Need | F16: Sarfatti wording; Wentz credential; Novak title; Story co-founder terms; no neighbor or celebrity references
A17: 14 | B17: C. Team | C17: Hiring plan and role definitions | D17: Ian / E57 | E17: Have (v1) | F17: Headcount sheet; placeholders flagged
A18: 15 | B18: C. Team | C18: Offer letter templates; PIIA / IP assignment for every hire and consultant | D18: Novak | E18: Need | F18: Theoretical-physicist consulting agreements included
A19: 16 | B19: C. Team | C19: Export-control screening (ITAR / EAR) for hardware and for foreign-national hires | D19: Novak / EHS | E19: Need | F19: Deemed-export review before physicist offers go out; relevant to IQT and any federal path
A20: 17 | B20: D. Intellectual property | C20: IP assignment from founders and McLean Companies to EnergyWave, Inc. | D20: Novak | E20: Need
A21: 18 | B21: D. Intellectual property | C21: K&L Gates IP strategy memo; prior-art file on historically claimed configurations under test | D21: Majewski | E21: Need | F21: Freedom-to-operate on anything that reaches Gate 3
A22: 19 | B22: E. Financial | C22: 36-month driver-based model, use of funds, gate tranches | D22: E57 / Ian | E22: Have (v1) | F22: This workbook; every Placeholder validated before circulation
A23: 20 | B23: E. Financial | C23: Pre-formation expense ledger (McLean Companies) and reimbursement agreement | D23: Ian / E57 | E23: Need
A24: 21 | B24: E. Financial | C24: Bank accounts, signatories, controls, expense policy | D24: E57 | E24: Need
A25: 22 | B25: E. Financial | C25: Budget-vs-actual and board reporting cadence | D25: E57 | E25: Need
A26: 23 | B26: E. Financial | C26: Audit / tax engagement; Form 990 plan for affiliates | D26: E57 | E26: Need
A27: 24 | B27: F. Legal & compliance | C27: 501(c)(3) private-benefit / inurement mitigation memo (nine items) | D27: Novak | E27: Have | F27: Counsel package prepared
A28: 25 | B28: F. Legal & compliance | C28: GovThink Institute determination status | D28: Novak | E28: In progress
A29: 26 | B29: F. Legal & compliance | C29: pinnacle.blog formation, mission, board, relationship memo | D29: Ian | E29: Need
A30: 27 | B30: F. Legal & compliance | C30: Insurance binders (D&O, GL, property, testing liability, workers' comp) | D30: E57 / broker | E30: Need
A31: 28 | B31: F. Legal & compliance | C31: Lab safety / EHS plan; hazard review process; incident reporting | D31: EHS Officer | E31: Need | F31: Precedes any bench work
A32: 29 | B32: F. Legal & compliance | C32: Lease and tenant-improvement scope | D32: Ian / Novak | E32: Need
A33: 30 | B33: G. Technical program | C33: Three-gate protocol document (Characterize → Conservation-test → Extract or retire, published) | D33: Ian | E33: Have | F33: DoD white paper basis
A34: 31 | B34: G. Technical program | C34: Language audit of every packet document | D34: Ian | E34: Need | F34: 'as claimed / never independently verified / under test'; no named method as the objective; no performance figures; no over-unity framing
A35: 32 | B35: G. Technical program | C35: Instrumentation & calibration plan; independent replication plan; null-results publication policy | D35: Test engineer / Ian | E35: Need
A36: 33 | B36: G. Technical program | C36: UCI / NFCRC facility-use or sponsored-research agreement | D36: Ian | E36: Need | F36: Cost line C12 exists only if executed; also unlocks STTR
A37: 34 | B37: H. Government | C37: SAM.gov registration (UEI / CAGE) | D37: Ian | E37: Need | F37: Prerequisite for any federal submission
A38: 35 | B38: H. Government | C38: DoD white paper (McLean Companies letterhead) | D38: Ian | E38: Have | F38: Flagged verifications still open
A39: 36 | B39: H. Government | C39: TRIAGE executive summary | D39: Ian | E39: Have (draft) | F39: File after SAM.gov
A40: 37 | B40: H. Government | C40: University STTR partner | D40: Ian | E40: Need
B42: Status counts
B43: Have* | C43: =COUNTIF($E$4:$E$40,"Have*") -> 8
B44: In progress | C44: =COUNTIF($E$4:$E$40,"In progress") -> 2
B45: Need | C45: =COUNTIF($E$4:$E$40,"Need") -> 26
B46: Blocked | C46: =COUNTIF($E$4:$E$40,"Blocked") -> 1
